Workbook

Sheet Lists
A1: Not Started | B1: Critical | C1: Phase 1 - Foundation | D1: All
A2: In Progress | B2: High | C2: Phase 2 - Core Operations | D2: All (varies by source type)
A3: Blocked | B3: Medium | C3: Phase 3 - Finance & Control | D3: Owned Only
A4: Done | B4: Low | C4: Phase 4 - Integrations & BI | D4: Rented Only
A5: Deferred | D5: Rider-Owned Only
D6: Owned + Rented

Sheet Overview
A1: 3PL Mixed-Fleet System Build Checklist
J2: Total Tasks | N2: In Progress
A3: Purpose | B3: This workbook converts the mixed-fleet system design into a practical task tracker and logic checklist for HR, Operations, Fleet, Finance, Compliance, Integrations, and BI. | J3: =COUNTIF('Master Tracker'!$B:$B,"<>")-1 -> 109 | N3: =COUNTIF('Master Tracker'!$K:$K,"In Progress") -> 0
J5: Completed | N5: Blocked
A6: How to use | J6: =COUNTIF('Master Tracker'!$K:$K,"Done") -> 0 | N6: =COUNTIF('Master Tracker'!$K:$K,"Blocked") -> 0
B7: 1) Update Owner, Target Date, Status and Notes in the Master Tracker.
B8: 2) Use the module tabs as linked reference views by department. | J8: Completion %
B9: 3) Review the Logic Register before development to lock core rules. | J9: =IF(J3=0,0,J6/J3) -> 0
B10: 4) Vehicle source types assumed: RENTED_BY_COMPANY, OWNED_BY_COMPANY, RIDER_OWNED.
A13: Module Progress Summary | F13: Status Legend
A14: Module | B14: Total Tasks | C14: Done | D14: % Complete | F14: Not Started
A15: Data Model | B15: =COUNTIF('Master Tracker'!$C:$C,A15) -> 18 | C15: =COUNTIFS('Master Tracker'!$C:$C,A15,'Master Tracker'!$K:$K,"Done") -> 0 | D15: =IF(B15=0,0,C15/B15) -> 0 | F15: In Progress
A16: HR | B16: =COUNTIF('Master Tracker'!$C:$C,A16) -> 14 | C16: =COUNTIFS('Master Tracker'!$C:$C,A16,'Master Tracker'!$K:$K,"Done") -> 0 | D16: =IF(B16=0,0,C16/B16) -> 0 | F16: Blocked
A17: Operations | B17: =COUNTIF('Master Tracker'!$C:$C,A17) -> 14 | C17: =COUNTIFS('Master Tracker'!$C:$C,A17,'Master Tracker'!$K:$K,"Done") -> 0 | D17: =IF(B17=0,0,C17/B17) -> 0 | F17: Done
A18: Fleet | B18: =COUNTIF('Master Tracker'!$C:$C,A18) -> 15 | C18: =COUNTIFS('Master Tracker'!$C:$C,A18,'Master Tracker'!$K:$K,"Done") -> 0 | D18: =IF(B18=0,0,C18/B18) -> 0 | F18: Deferred
A19: Finance | B19: =COUNTIF('Master Tracker'!$C:$C,A19) -> 15 | C19: =COUNTIFS('Master Tracker'!$C:$C,A19,'Master Tracker'!$K:$K,"Done") -> 0 | D19: =IF(B19=0,0,C19/B19) -> 0
A20: Compliance | B20: =COUNTIF('Master Tracker'!$C:$C,A20) -> 12 | C20: =COUNTIFS('Master Tracker'!$C:$C,A20,'Master Tracker'!$K:$K,"Done") -> 0 | D20: =IF(B20=0,0,C20/B20) -> 0
A21: Integrations | B21: =COUNTIF('Master Tracker'!$C:$C,A21) -> 10 | C21: =COUNTIFS('Master Tracker'!$C:$C,A21,'Master Tracker'!$K:$K,"Done") -> 0 | D21: =IF(B21=0,0,C21/B21) -> 0
A22: BI & Reports | B22: =COUNTIF('Master Tracker'!$C:$C,A22) -> 11 | C22: =COUNTIFS('Master Tracker'!$C:$C,A22,'Master Tracker'!$K:$K,"Done") -> 0 | D22: =IF(B22=0,0,C22/B22) -> 0
A24: Last updated | B24: 46130.552

Sheet Master Tracker
A1: Master Tracker
A2: Source-of-truth execution tracker. Update Status, Owner, Target Date and Notes here; department tabs reference this sheet.
A5: Checklist | B5: Task ID | C5: Module | D5: Workstream | E5: Task | F5: Deliverable / Logic | G5: Source Type Impact | H5: Priority | I5: Phase | J5: Dependency | K5: Status | L5: Owner | M5: Target Date | N5: Notes
A6: =IF(K6="Done","☑","☐") -> ☐ | B6: T-001 | C6: Data Model | D6: Core Entities | E6: Define master ID strategy and audit fields across all tables | F6: Common primary keys, created/updated timestamps, soft delete and source tracking | G6: All | H6: Critical | I6: Phase 1 - Foundation | K6: Not Started
A7: =IF(K7="Done","☑","☐") -> ☐ | B7: T-002 | C7: Data Model | D7: Core Entities | E7: Create Riders entity and base profile fields | F7: Personal details, license, visa, bank, status and rider category | G7: All | H7: Critical | I7: Phase 1 - Foundation | K7: Not Started
A8: =IF(K8="Done","☑","☐") -> ☐ | B8: T-003 | C8: Data Model | D8: Core Entities | E8: Create Vehicles entity with mixed-fleet attributes | F8: Plate, make/model, status, compliance dates and current assignment | G8: All | H8: Critical | I8: Phase 1 - Foundation | K8: Not Started
A9: =IF(K9="Done","☑","☐") -> ☐ | B9: T-004 | C9: Data Model | D9: Mixed Fleet Logic | E9: Add vehicle_source_type enumeration | F9: RENTED_BY_COMPANY, OWNED_BY_COMPANY, RIDER_OWNED | G9: All | H9: Critical | I9: Phase 1 - Foundation | K9: Not Started
A10: =IF(K10="Done","☑","☐") -> ☐ | B10: T-005 | C10: Data Model | D10: Mixed Fleet Logic | E10: Create Vehicle_Source_Details entity | F10: Ownership, supplier, purchase/rent cost, responsibilities and contract dates | G10: All (varies by source type) | H10: Critical | I10: Phase 1 - Foundation | K10: Not Started
A11: =IF(K11="Done","☑","☐") -> ☐ | B11: T-006 | C11: Data Model | D11: Assignments | E11: Create Rider_Vehicle_Assignments history table | F11: Track assignment start/end, aggregator, client and reason for reassignment | G11: All | H11: Critical | I11: Phase 1 - Foundation | K11: Not Started
A12: =IF(K12="Done","☑","☐") -> ☐ | B12: T-007 | C12: Data Model | D12: Commercial Data | E12: Create Clients entity | F12: 3PL customer / legal entity records for multi-client support | G12: All | H12: High | I12: Phase 1 - Foundation | K12: Not Started
A13: =IF(K13="Done","☑","☐") -> ☐ | B13: T-008 | C13: Data Model | D13: Commercial Data | E13: Create Aggregators entity | F13: Talabat, Jahez, Keeta and any future partner configuration | G13: All | H13: Critical | I13: Phase 1 - Foundation | K13: Not Started
A14: =IF(K14="Done","☑","☐") -> ☐ | B14: T-009 | C14: Data Model | D14: Commercial Data | E14: Create Contracts entity | F14: Rates, validity dates, billing terms and service rules by client / aggregator | G14: All | H14: Critical | I14: Phase 2 - Core Operations | K14: Not Started
A15: =IF(K15="Done","☑","☐") -> ☐ | B15: T-010 | C15: Data Model | D15: Operations Data | E15: Create Shifts entity | F15: Shift types, scheduled hours, attendance linkage and allocation rules | G15: All | H15: High | I15: Phase 2 - Core Operations | K15: Not Started
A16: =IF(K16="Done","☑","☐") -> ☐ | B16: T-011 | C16: Data Model | D16: Operations Data | E16: Create Attendance entity | F16: GPS check-in/out, worked hours, exceptions and approval status | G16: All | H16: Critical | I16: Phase 2 - Core Operations | K16: Not Started
A17: =IF(K17="Done","☑","☐") -> ☐ | B17: T-012 | C17: Data Model | D17: Operations Data | E17: Create Orders entity | F17: External order ID, rider, vehicle, distance, revenue, payout and source import batch | G17: All | H17: Critical | I17: Phase 2 - Core Operations | K17: Not Started
... A114: =IF(K114="Done","☑","☐") -> ☐ | B114: T-109 | C114: BI & Reports | D114: Compliance Reports | E114: Define compliance risk report | F114: Upcoming expiries, blocked assets, blocked riders and unresolved incidents | G114: All | H114: Medium | I114: Phase 4 - Integrations & BI | K114: Not Started

Sheet Data Model
A1: Data Model Checklist
A2: Linked departmental view for Data Model. Edit the Master Tracker tab as the source of truth; this tab mirrors those rows for focused review.
A5: Checklist | B5: Task ID | C5: Module | D5: Workstream | E5: Task | F5: Deliverable / Logic | G5: Source Type Impact | H5: Priority | I5: Phase | J5: Dependency | K5: Status | L5: Owner | M5: Target Date | N5: Notes
A6: =IF('Master Tracker'!A6="","",'Master Tracker'!A6) -> ☐ | B6: =IF('Master Tracker'!B6="","",'Master Tracker'!B6) -> T-001 | C6: =IF('Master Tracker'!C6="","",'Master Tracker'!C6) -> Data Model | D6: =IF('Master Tracker'!D6="","",'Master Tracker'!D6) -> Core Entities | E6: =IF('Master Tracker'!E6="","",'Master Tracker'!E6) -> Define master ID strategy and audit fields across all tables | F6: =IF('Master Tracker'!F6="","",'Master Tracker'!F6) -> Common primary keys, created/updated timestamps, soft delete and source tracking | G6: =IF('Master Tracker'!G6="","",'Master Tracker'!G6) -> All | H6: =IF('Master Tracker'!H6="","",'Master Tracker'!H6) -> Critical | ... N6: =IF('Master Tracker'!N6="","",'Master Tracker'!N6)
A7: =IF('Master Tracker'!A7="","",'Master Tracker'!A7) -> ☐ | B7: =IF('Master Tracker'!B7="","",'Master Tracker'!B7) -> T-002 | C7: =IF('Master Tracker'!C7="","",'Master Tracker'!C7) -> Data Model | D7: =IF('Master Tracker'!D7="","",'Master Tracker'!D7) -> Core Entities | E7: =IF('Master Tracker'!E7="","",'Master Tracker'!E7) -> Create Riders entity and base profile fields | F7: =IF('Master Tracker'!F7="","",'Master Tracker'!F7) -> Personal details, license, visa, bank, status and rider category | G7: =IF('Master Tracker'!G7="","",'Master Tracker'!G7) -> All | H7: =IF('Master Tracker'!H7="","",'Master Tracker'!H7) -> Critical | ... N7: =IF('Master Tracker'!N7="","",'Master Tracker'!N7)
A8: =IF('Master Tracker'!A8="","",'Master Tracker'!A8) -> ☐ | B8: =IF('Master Tracker'!B8="","",'Master Tracker'!B8) -> T-003 | C8: =IF('Master Tracker'!C8="","",'Master Tracker'!C8) -> Data Model | D8: =IF('Master Tracker'!D8="","",'Master Tracker'!D8) -> Core Entities | E8: =IF('Master Tracker'!E8="","",'Master Tracker'!E8) -> Create Vehicles entity with mixed-fleet attributes | F8: =IF('Master Tracker'!F8="","",'Master Tracker'!F8) -> Plate, make/model, status, compliance dates and current assignment | G8: =IF('Master Tracker'!G8="","",'Master Tracker'!G8) -> All | H8: =IF('Master Tracker'!H8="","",'Master Tracker'!H8) -> Critical | ... N8: =IF('Master Tracker'!N8="","",'Master Tracker'!N8)
A9: =IF('Master Tracker'!A9="","",'Master Tracker'!A9) -> ☐ | B9: =IF('Master Tracker'!B9="","",'Master Tracker'!B9) -> T-004 | C9: =IF('Master Tracker'!C9="","",'Master Tracker'!C9) -> Data Model | D9: =IF('Master Tracker'!D9="","",'Master Tracker'!D9) -> Mixed Fleet Logic | E9: =IF('Master Tracker'!E9="","",'Master Tracker'!E9) -> Add vehicle_source_type enumeration | F9: =IF('Master Tracker'!F9="","",'Master Tracker'!F9) -> RENTED_BY_COMPANY, OWNED_BY_COMPANY, RIDER_OWNED | G9: =IF('Master Tracker'!G9="","",'Master Tracker'!G9) -> All | H9: =IF('Master Tracker'!H9="","",'Master Tracker'!H9) -> Critical | ... N9: =IF('Master Tracker'!N9="","",'Master Tracker'!N9)
A10: =IF('Master Tracker'!A10="","",'Master Tracker'!A10) -> ☐ | B10: =IF('Master Tracker'!B10="","",'Master Tracker'!B10) -> T-005 | C10: =IF('Master Tracker'!C10="","",'Master Tracker'!C10) -> Data Model | D10: =IF('Master Tracker'!D10="","",'Master Tracker'!D10) -> Mixed Fleet Logic | E10: =IF('Master Tracker'!E10="","",'Master Tracker'!E10) -> Create Vehicle_Source_Details entity | F10: =IF('Master Tracker'!F10="","",'Master Tracker'!F10) -> Ownership, supplier, purchase/rent cost, responsibilities and contract dates | G10: =IF('Master Tracker'!G10="","",'Master Tracker'!G10) -> All (varies by source type) | H10: =IF('Master Tracker'!H10="","",'Master Tracker'!H10) -> Critical | ... N10: =IF('Master Tracker'!N10="","",'Master Tracker'!N10)
A11: =IF('Master Tracker'!A11="","",'Master Tracker'!A11) -> ☐ | B11: =IF('Master Tracker'!B11="","",'Master Tracker'!B11) -> T-006 | C11: =IF('Master Tracker'!C11="","",'Master Tracker'!C11) -> Data Model | D11: =IF('Master Tracker'!D11="","",'Master Tracker'!D11) -> Assignments | E11: =IF('Master Tracker'!E11="","",'Master Tracker'!E11) -> Create Rider_Vehicle_Assignments history table | F11: =IF('Master Tracker'!F11="","",'Master Tracker'!F11) -> Track assignment start/end, aggregator, client and reason for reassignment | G11: =IF('Master Tracker'!G11="","",'Master Tracker'!G11) -> All | H11: =IF('Master Tracker'!H11="","",'Master Tracker'!H11) -> Critical | ... N11: =IF('Master Tracker'!N11="","",'Master Tracker'!N11)
A12: =IF('Master Tracker'!A12="","",'Master Tracker'!A12) -> ☐ | B12: =IF('Master Tracker'!B12="","",'Master Tracker'!B12) -> T-007 | C12: =IF('Master Tracker'!C12="","",'Master Tracker'!C12) -> Data Model | D12: =IF('Master Tracker'!D12="","",'Master Tracker'!D12) -> Commercial Data | E12: =IF('Master Tracker'!E12="","",'Master Tracker'!E12) -> Create Clients entity | F12: =IF('Master Tracker'!F12="","",'Master Tracker'!F12) -> 3PL customer / legal entity records for multi-client support | G12: =IF('Master Tracker'!G12="","",'Master Tracker'!G12) -> All | H12: =IF('Master Tracker'!H12="","",'Master Tracker'!H12) -> High | ... N12: =IF('Master Tracker'!N12="","",'Master Tracker'!N12)
A13: =IF('Master Tracker'!A13="","",'Master Tracker'!A13) -> ☐ | B13: =IF('Master Tracker'!B13="","",'Master Tracker'!B13) -> T-008 | C13: =IF('Master Tracker'!C13="","",'Master Tracker'!C13) -> Data Model | D13: =IF('Master Tracker'!D13="","",'Master Tracker'!D13) -> Commercial Data | E13: =IF('Master Tracker'!E13="","",'Master Tracker'!E13) -> Create Aggregators entity | F13: =IF('Master Tracker'!F13="","",'Master Tracker'!F13) -> Talabat, Jahez, Keeta and any future partner configuration | G13: =IF('Master Tracker'!G13="","",'Master Tracker'!G13) -> All | H13: =IF('Master Tracker'!H13="","",'Master Tracker'!H13) -> Critical | ... N13: =IF('Master Tracker'!N13="","",'Master Tracker'!N13)
A14: =IF('Master Tracker'!A14="","",'Master Tracker'!A14) -> ☐ | B14: =IF('Master Tracker'!B14="","",'Master Tracker'!B14) -> T-009 | C14: =IF('Master Tracker'!C14="","",'Master Tracker'!C14) -> Data Model | D14: =IF('Master Tracker'!D14="","",'Master Tracker'!D14) -> Commercial Data | E14: =IF('Master Tracker'!E14="","",'Master Tracker'!E14) -> Create Contracts entity | F14: =IF('Master Tracker'!F14="","",'Master Tracker'!F14) -> Rates, validity dates, billing terms and service rules by client / aggregator | G14: =IF('Master Tracker'!G14="","",'Master Tracker'!G14) -> All | H14: =IF('Master Tracker'!H14="","",'Master Tracker'!H14) -> Critical | ... N14: =IF('Master Tracker'!N14="","",'Master Tracker'!N14)
A15: =IF('Master Tracker'!A15="","",'Master Tracker'!A15) -> ☐ | B15: =IF('Master Tracker'!B15="","",'Master Tracker'!B15) -> T-010 | C15: =IF('Master Tracker'!C15="","",'Master Tracker'!C15) -> Data Model | D15: =IF('Master Tracker'!D15="","",'Master Tracker'!D15) -> Operations Data | E15: =IF('Master Tracker'!E15="","",'Master Tracker'!E15) -> Create Shifts entity | F15: =IF('Master Tracker'!F15="","",'Master Tracker'!F15) -> Shift types, scheduled hours, attendance linkage and allocation rules | G15: =IF('Master Tracker'!G15="","",'Master Tracker'!G15) -> All | H15: =IF('Master Tracker'!H15="","",'Master Tracker'!H15) -> High | ... N15: =IF('Master Tracker'!N15="","",'Master Tracker'!N15)
A16: =IF('Master Tracker'!A16="","",'Master Tracker'!A16) -> ☐ | B16: =IF('Master Tracker'!B16="","",'Master Tracker'!B16) -> T-011 | C16: =IF('Master Tracker'!C16="","",'Master Tracker'!C16) -> Data Model | D16: =IF('Master Tracker'!D16="","",'Master Tracker'!D16) -> Operations Data | E16: =IF('Master Tracker'!E16="","",'Master Tracker'!E16) -> Create Attendance entity | F16: =IF('Master Tracker'!F16="","",'Master Tracker'!F16) -> GPS check-in/out, worked hours, exceptions and approval status | G16: =IF('Master Tracker'!G16="","",'Master Tracker'!G16) -> All | H16: =IF('Master Tracker'!H16="","",'Master Tracker'!H16) -> Critical | ... N16: =IF('Master Tracker'!N16="","",'Master Tracker'!N16)
A17: =IF('Master Tracker'!A17="","",'Master Tracker'!A17) -> ☐ | B17: =IF('Master Tracker'!B17="","",'Master Tracker'!B17) -> T-012 | C17: =IF('Master Tracker'!C17="","",'Master Tracker'!C17) -> Data Model | D17: =IF('Master Tracker'!D17="","",'Master Tracker'!D17) -> Operations Data | E17: =IF('Master Tracker'!E17="","",'Master Tracker'!E17) -> Create Orders entity | F17: =IF('Master Tracker'!F17="","",'Master Tracker'!F17) -> External order ID, rider, vehicle, distance, revenue, payout and source import batch | G17: =IF('Master Tracker'!G17="","",'Master Tracker'!G17) -> All | H17: =IF('Master Tracker'!H17="","",'Master Tracker'!H17) -> Critical | ... N17: =IF('Master Tracker'!N17="","",'Master Tracker'!N17)
... A23: =IF('Master Tracker'!A23="","",'Master Tracker'!A23) -> ☐ | B23: =IF('Master Tracker'!B23="","",'Master Tracker'!B23) -> T-018 | C23: =IF('Master Tracker'!C23="","",'Master Tracker'!C23) -> Data Model | D23: =IF('Master Tracker'!D23="","",'Master Tracker'!D23) -> Security | E23: =IF('Master Tracker'!E23="","",'Master Tracker'!E23) -> Design user roles and permission matrix | F23: =IF('Master Tracker'!F23="","",'Master Tracker'!F23) -> HR, Ops, Fleet, Finance, Compliance, Admin and Executive access rights | G23: =IF('Master Tracker'!G23="","",'Master Tracker'!G23) -> All | H23: =IF('Master Tracker'!H23="","",'Master Tracker'!H23) -> High | ... N23: =IF('Master Tracker'!N23="","",'Master Tracker'!N23)

Sheet HR
A1: HR Checklist
A2: Linked departmental view for HR. Edit the Master Tracker tab as the source of truth; this tab mirrors those rows for focused review.
A5: Checklist | B5: Task ID | C5: Module | D5: Workstream | E5: Task | F5: Deliverable / Logic | G5: Source Type Impact | H5: Priority | I5: Phase | J5: Dependency | K5: Status | L5: Owner | M5: Target Date | N5: Notes
A6: =IF('Master Tracker'!A24="","",'Master Tracker'!A24) -> ☐ | B6: =IF('Master Tracker'!B24="","",'Master Tracker'!B24) -> T-019 | C6: =IF('Master Tracker'!C24="","",'Master Tracker'!C24) -> HR | D6: =IF('Master Tracker'!D24="","",'Master Tracker'!D24) -> Onboarding | E6: =IF('Master Tracker'!E24="","",'Master Tracker'!E24) -> Define rider onboarding workflow | F6: =IF('Master Tracker'!F24="","",'Master Tracker'!F24) -> Steps from application to activation including document approval | G6: =IF('Master Tracker'!G24="","",'Master Tracker'!G24) -> All | H6: =IF('Master Tracker'!H24="","",'Master Tracker'!H24) -> Critical | ... N6: =IF('Master Tracker'!N24="","",'Master Tracker'!N24)
A7: =IF('Master Tracker'!A25="","",'Master Tracker'!A25) -> ☐ | B7: =IF('Master Tracker'!B25="","",'Master Tracker'!B25) -> T-020 | C7: =IF('Master Tracker'!C25="","",'Master Tracker'!C25) -> HR | D7: =IF('Master Tracker'!D25="","",'Master Tracker'!D25) -> Onboarding | E7: =IF('Master Tracker'!E25="","",'Master Tracker'!E25) -> Create rider category rules based on transport model | F7: =IF('Master Tracker'!F25="","",'Master Tracker'!F25) -> Different handling for company-bike riders vs rider-owned riders | G7: =IF('Master Tracker'!G25="","",'Master Tracker'!G25) -> All (varies by source type) | H7: =IF('Master Tracker'!H25="","",'Master Tracker'!H25) -> Critical | ... N7: =IF('Master Tracker'!N25="","",'Master Tracker'!N25)
A8: =IF('Master Tracker'!A26="","",'Master Tracker'!A26) -> ☐ | B8: =IF('Master Tracker'!B26="","",'Master Tracker'!B26) -> T-021 | C8: =IF('Master Tracker'!C26="","",'Master Tracker'!C26) -> HR | D8: =IF('Master Tracker'!D26="","",'Master Tracker'!D26) -> Onboarding | E8: =IF('Master Tracker'!E26="","",'Master Tracker'!E26) -> Build document collection checklist | F8: =IF('Master Tracker'!F26="","",'Master Tracker'!F26) -> CPR/ID, visa, license, contract, bank, emergency contact | G8: =IF('Master Tracker'!G26="","",'Master Tracker'!G26) -> All | H8: =IF('Master Tracker'!H26="","",'Master Tracker'!H26) -> High | ... N8: =IF('Master Tracker'!N26="","",'Master Tracker'!N26)
A9: =IF('Master Tracker'!A27="","",'Master Tracker'!A27) -> ☐ | B9: =IF('Master Tracker'!B27="","",'Master Tracker'!B27) -> T-022 | C9: =IF('Master Tracker'!C27="","",'Master Tracker'!C27) -> HR | D9: =IF('Master Tracker'!D27="","",'Master Tracker'!D27) -> Contracts | E9: =IF('Master Tracker'!E27="","",'Master Tracker'!E27) -> Prepare employment / service contract templates | F9: =IF('Master Tracker'!F27="","",'Master Tracker'!F27) -> Separate clauses for company vehicle, rented vehicle and rider-owned vehicle cases | G9: =IF('Master Tracker'!G27="","",'Master Tracker'!G27) -> All (varies by source type) | H9: =IF('Master Tracker'!H27="","",'Master Tracker'!H27) -> High | ... N9: =IF('Master Tracker'!N27="","",'Master Tracker'!N27)
A10: =IF('Master Tracker'!A28="","",'Master Tracker'!A28) -> ☐ | B10: =IF('Master Tracker'!B28="","",'Master Tracker'!B28) -> T-023 | C10: =IF('Master Tracker'!C28="","",'Master Tracker'!C28) -> HR | D10: =IF('Master Tracker'!D28="","",'Master Tracker'!D28) -> Contracts | E10: =IF('Master Tracker'!E28="","",'Master Tracker'!E28) -> Capture deposit / deduction agreements where applicable | F10: =IF('Master Tracker'!F28="","",'Master Tracker'!F28) -> Vehicle damage, uniform, equipment or advance recovery logic | G10: =IF('Master Tracker'!G28="","",'Master Tracker'!G28) -> Owned + Rented | H10: =IF('Master Tracker'!H28="","",'Master Tracker'!H28) -> High | ... N10: =IF('Master Tracker'!N28="","",'Master Tracker'!N28)
A11: =IF('Master Tracker'!A29="","",'Master Tracker'!A29) -> ☐ | B11: =IF('Master Tracker'!B29="","",'Master Tracker'!B29) -> T-024 | C11: =IF('Master Tracker'!C29="","",'Master Tracker'!C29) -> HR | D11: =IF('Master Tracker'!D29="","",'Master Tracker'!D29) -> Compliance | E11: =IF('Master Tracker'!E29="","",'Master Tracker'!E29) -> Track visa and license expiry alerts | F11: =IF('Master Tracker'!F29="","",'Master Tracker'!F29) -> Prevent activation of riders with invalid legal documents | G11: =IF('Master Tracker'!G29="","",'Master Tracker'!G29) -> All | H11: =IF('Master Tracker'!H29="","",'Master Tracker'!H29) -> Critical | ... N11: =IF('Master Tracker'!N29="","",'Master Tracker'!N29)
A12: =IF('Master Tracker'!A30="","",'Master Tracker'!A30) -> ☐ | B12: =IF('Master Tracker'!B30="","",'Master Tracker'!B30) -> T-025 | C12: =IF('Master Tracker'!C30="","",'Master Tracker'!C30) -> HR | D12: =IF('Master Tracker'!D30="","",'Master Tracker'!D30) -> Payroll Inputs | E12: =IF('Master Tracker'!E30="","",'Master Tracker'!E30) -> Define pay components and earning rules | F12: =IF('Master Tracker'!F30="","",'Master Tracker'!F30) -> Fixed salary, per-order, extra km, allowance, deductions and incentives | G12: =IF('Master Tracker'!G30="","",'Master Tracker'!G30) -> All (varies by source type) | H12: =IF('Master Tracker'!H30="","",'Master Tracker'!H30) -> Critical | ... N12: =IF('Master Tracker'!N30="","",'Master Tracker'!N30)
A13: =IF('Master Tracker'!A31="","",'Master Tracker'!A31) -> ☐ | B13: =IF('Master Tracker'!B31="","",'Master Tracker'!B31) -> T-026 | C13: =IF('Master Tracker'!C31="","",'Master Tracker'!C31) -> HR | D13: =IF('Master Tracker'!D31="","",'Master Tracker'!D31) -> Payroll Inputs | E13: =IF('Master Tracker'!E31="","",'Master Tracker'!E31) -> Define own-bike allowance policy | F13: =IF('Master Tracker'!F31="","",'Master Tracker'!F31) -> When and how rider-owned vehicle riders receive transport allowance | G13: =IF('Master Tracker'!G31="","",'Master Tracker'!G31) -> Rider-Owned Only | H13: =IF('Master Tracker'!H31="","",'Master Tracker'!H31) -> High | ... N13: =IF('Master Tracker'!N31="","",'Master Tracker'!N31)
A14: =IF('Master Tracker'!A32="","",'Master Tracker'!A32) -> ☐ | B14: =IF('Master Tracker'!B32="","",'Master Tracker'!B32) -> T-027 | C14: =IF('Master Tracker'!C32="","",'Master Tracker'!C32) -> HR | D14: =IF('Master Tracker'!D32="","",'Master Tracker'!D32) -> Payroll Inputs | E14: =IF('Master Tracker'!E32="","",'Master Tracker'!E32) -> Define company-bike deduction policy | F14: =IF('Master Tracker'!F32="","",'Master Tracker'!F32) -> Monthly/daily deduction or damage recovery for company vehicles | G14: =IF('Master Tracker'!G32="","",'Master Tracker'!G32) -> Owned + Rented | H14: =IF('Master Tracker'!H32="","",'Master Tracker'!H32) -> High | ... N14: =IF('Master Tracker'!N32="","",'Master Tracker'!N32)
A15: =IF('Master Tracker'!A33="","",'Master Tracker'!A33) -> ☐ | B15: =IF('Master Tracker'!B33="","",'Master Tracker'!B33) -> T-028 | C15: =IF('Master Tracker'!C33="","",'Master Tracker'!C33) -> HR | D15: =IF('Master Tracker'!D33="","",'Master Tracker'!D33) -> Attendance | E15: =IF('Master Tracker'!E33="","",'Master Tracker'!E33) -> Design attendance approval flow | F15: =IF('Master Tracker'!F33="","",'Master Tracker'!F33) -> Missed check-in, manual override, lateness and supervisor approval | G15: =IF('Master Tracker'!G33="","",'Master Tracker'!G33) -> All | H15: =IF('Master Tracker'!H33="","",'Master Tracker'!H33) -> High | ... N15: =IF('Master Tracker'!N33="","",'Master Tracker'!N33)
A16: =IF('Master Tracker'!A34="","",'Master Tracker'!A34) -> ☐ | B16: =IF('Master Tracker'!B34="","",'Master Tracker'!B34) -> T-029 | C16: =IF('Master Tracker'!C34="","",'Master Tracker'!C34) -> HR | D16: =IF('Master Tracker'!D34="","",'Master Tracker'!D34) -> People Ops | E16: =IF('Master Tracker'!E34="","",'Master Tracker'!E34) -> Create disciplinary process linked to vehicle misuse | F16: =IF('Master Tracker'!F34="","",'Master Tracker'!F34) -> Late return, reckless use, damage and repeated non-compliance | G16: =IF('Master Tracker'!G34="","",'Master Tracker'!G34) -> Owned + Rented | H16: =IF('Master Tracker'!H34="","",'Master Tracker'!H34) -> Medium | ... N16: =IF('Master Tracker'!N34="","",'Master Tracker'!N34)
A17: =IF('Master Tracker'!A35="","",'Master Tracker'!A35) -> ☐ | B17: =IF('Master Tracker'!B35="","",'Master Tracker'!B35) -> T-030 | C17: =IF('Master Tracker'!C35="","",'Master Tracker'!C35) -> HR | D17: =IF('Master Tracker'!D35="","",'Master Tracker'!D35) -> People Ops | E17: =IF('Master Tracker'!E35="","",'Master Tracker'!E35) -> Create offboarding checklist | F17: =IF('Master Tracker'!F35="","",'Master Tracker'!F35) -> Final payroll, asset return, account disablement and document archive | G17: =IF('Master Tracker'!G35="","",'Master Tracker'!G35) -> All | H17: =IF('Master Tracker'!H35="","",'Master Tracker'!H35) -> High | ... N17: =IF('Master Tracker'!N35="","",'Master Tracker'!N35)
... A19: =IF('Master Tracker'!A37="","",'Master Tracker'!A37) -> ☐ | B19: =IF('Master Tracker'!B37="","",'Master Tracker'!B37) -> T-032 | C19: =IF('Master Tracker'!C37="","",'Master Tracker'!C37) -> HR | D19: =IF('Master Tracker'!D37="","",'Master Tracker'!D37) -> Dashboard | E19: =IF('Master Tracker'!E37="","",'Master Tracker'!E37) -> Define HR dashboard metrics | F19: =IF('Master Tracker'!F37="","",'Master Tracker'!F37) -> Headcount, active riders, expired docs, churn and payroll exceptions | G19: =IF('Master Tracker'!G37="","",'Master Tracker'!G37) -> All | H19: =IF('Master Tracker'!H37="","",'Master Tracker'!H37) -> Medium | ... N19: =IF('Master Tracker'!N37="","",'Master Tracker'!N37)

Sheet Operations
A1: Operations Checklist
A2: Linked departmental view for Operations. Edit the Master Tracker tab as the source of truth; this tab mirrors those rows for focused review.
A5: Checklist | B5: Task ID | C5: Module | D5: Workstream | E5: Task | F5: Deliverable / Logic | G5: Source Type Impact | H5: Priority | I5: Phase | J5: Dependency | K5: Status | L5: Owner | M5: Target Date | N5: Notes
A6: =IF('Master Tracker'!A38="","",'Master Tracker'!A38) -> ☐ | B6: =IF('Master Tracker'!B38="","",'Master Tracker'!B38) -> T-033 | C6: =IF('Master Tracker'!C38="","",'Master Tracker'!C38) -> Operations | D6: =IF('Master Tracker'!D38="","",'Master Tracker'!D38) -> Shift Planning | E6: =IF('Master Tracker'!E38="","",'Master Tracker'!E38) -> Build shift planning and roster structure | F6: =IF('Master Tracker'!F38="","",'Master Tracker'!F38) -> Daily/weekly rider scheduling by client and aggregator | G6: =IF('Master Tracker'!G38="","",'Master Tracker'!G38) -> All | H6: =IF('Master Tracker'!H38="","",'Master Tracker'!H38) -> Critical | ... N6: =IF('Master Tracker'!N38="","",'Master Tracker'!N38)
A7: =IF('Master Tracker'!A39="","",'Master Tracker'!A39) -> ☐ | B7: =IF('Master Tracker'!B39="","",'Master Tracker'!B39) -> T-034 | C7: =IF('Master Tracker'!C39="","",'Master Tracker'!C39) -> Operations | D7: =IF('Master Tracker'!D39="","",'Master Tracker'!D39) -> Shift Planning | E7: =IF('Master Tracker'!E39="","",'Master Tracker'!E39) -> Create rider eligibility check before shift activation | F7: =IF('Master Tracker'!F39="","",'Master Tracker'!F39) -> Only activate riders with valid docs and approved vehicle | G7: =IF('Master Tracker'!G39="","",'Master Tracker'!G39) -> All | H7: =IF('Master Tracker'!H39="","",'Master Tracker'!H39) -> Critical | ... N7: =IF('Master Tracker'!N39="","",'Master Tracker'!N39)
A8: =IF('Master Tracker'!A40="","",'Master Tracker'!A40) -> ☐ | B8: =IF('Master Tracker'!B40="","",'Master Tracker'!B40) -> T-035 | C8: =IF('Master Tracker'!C40="","",'Master Tracker'!C40) -> Operations | D8: =IF('Master Tracker'!D40="","",'Master Tracker'!D40) -> Allocation | E8: =IF('Master Tracker'!E40="","",'Master Tracker'!E40) -> Design rider allocation rules by aggregator | F8: =IF('Master Tracker'!F40="","",'Master Tracker'!F40) -> Talabat / Jahez / Keeta assignment logic and eligibility mapping | G8: =IF('Master Tracker'!G40="","",'Master Tracker'!G40) -> All | H8: =IF('Master Tracker'!H40="","",'Master Tracker'!H40) -> Critical | ... N8: =IF('Master Tracker'!N40="","",'Master Tracker'!N40)
A9: =IF('Master Tracker'!A41="","",'Master Tracker'!A41) -> ☐ | B9: =IF('Master Tracker'!B41="","",'Master Tracker'!B41) -> T-036 | C9: =IF('Master Tracker'!C41="","",'Master Tracker'!C41) -> Operations | D9: =IF('Master Tracker'!D41="","",'Master Tracker'!D41) -> Allocation | E9: =IF('Master Tracker'!E41="","",'Master Tracker'!E41) -> Build rider + vehicle pairing workflow | F9: =IF('Master Tracker'!F41="","",'Master Tracker'!F41) -> Assign compliant available vehicle to rider for active shift | G9: =IF('Master Tracker'!G41="","",'Master Tracker'!G41) -> Owned + Rented | H9: =IF('Master Tracker'!H41="","",'Master Tracker'!H41) -> High | ... N9: =IF('Master Tracker'!N41="","",'Master Tracker'!N41)
A10: =IF('Master Tracker'!A42="","",'Master Tracker'!A42) -> ☐ | B10: 36-1 | C10: =IF('Master Tracker'!C42="","",'Master Tracker'!C42) -> Operations | D10: Allocation | E10: Replace Vehicle of Rider | F10: in case vehicle issues ability to temp./ perm replace the vehicle | G10: =IF('Master Tracker'!G41="","",'Master Tracker'!G41) -> Owned + Rented | H10: =IF('Master Tracker'!H42="","",'Master Tracker'!H42) -> High | I10: =IF('Master Tracker'!I42="","",'Master Tracker'!I42) -> Phase 4 - Integrations & BI | J10: =IF('Master Tracker'!J42="","",'Master Tracker'!J42) | K10: =IF('Master Tracker'!K42="","",'Master Tracker'!K42) -> Not Started | L10: =IF('Master Tracker'!L42="","",'Master Tracker'!L42) | M10: =IF('Master Tracker'!M42="","",'Master Tracker'!M42) | N10: =IF('Master Tracker'!N42="","",'Master Tracker'!N42)
A11: =IF('Master Tracker'!A42="","",'Master Tracker'!A42) -> ☐ | B11: =IF('Master Tracker'!B42="","",'Master Tracker'!B42) -> T-037 | C11: =IF('Master Tracker'!C42="","",'Master Tracker'!C42) -> Operations | D11: =IF('Master Tracker'!D42="","",'Master Tracker'!D42) -> Live Control | E11: =IF('Master Tracker'!E42="","",'Master Tracker'!E42) -> Design live operations control tower view | F11: =IF('Master Tracker'!F42="","",'Master Tracker'!F42) -> Online riders, active orders, issues, idle riders and replacement needs | G11: =IF('Master Tracker'!G42="","",'Master Tracker'!G42) -> All | H11: =IF('Master Tracker'!H42="","",'Master Tracker'!H42) -> High | ... N11: =IF('Master Tracker'!N42="","",'Master Tracker'!N42)
A12: =IF('Master Tracker'!A43="","",'Master Tracker'!A43) -> ☐ | B12: =IF('Master Tracker'!B43="","",'Master Tracker'!B43) -> T-038 | C12: =IF('Master Tracker'!C43="","",'Master Tracker'!C43) -> Operations | D12: =IF('Master Tracker'!D43="","",'Master Tracker'!D43) -> Live Control | E12: =IF('Master Tracker'!E43="","",'Master Tracker'!E43) -> Create breakdown escalation workflow | F12: =IF('Master Tracker'!F43="","",'Master Tracker'!F43) -> Different path for owned, rented and rider-owned vehicle incidents | G12: =IF('Master Tracker'!G43="","",'Master Tracker'!G43) -> All (varies by source type) | H12: =IF('Master Tracker'!H43="","",'Master Tracker'!H43) -> Critical | ... N12: =IF('Master Tracker'!N43="","",'Master Tracker'!N43)
A13: =IF('Master Tracker'!A44="","",'Master Tracker'!A44) -> ☐ | B13: =IF('Master Tracker'!B44="","",'Master Tracker'!B44) -> T-039 | C13: =IF('Master Tracker'!C44="","",'Master Tracker'!C44) -> Operations | D13: =IF('Master Tracker'!D44="","",'Master Tracker'!D44) -> Attendance | E13: =IF('Master Tracker'!E44="","",'Master Tracker'!E44) -> Connect attendance to operations roster | F13: =IF('Master Tracker'!F44="","",'Master Tracker'!F44) -> Show no-shows, late arrivals and active shift status in ops view | G13: =IF('Master Tracker'!G44="","",'Master Tracker'!G44) -> All | H13: =IF('Master Tracker'!H44="","",'Master Tracker'!H44) -> High | ... N13: =IF('Master Tracker'!N44="","",'Master Tracker'!N44)
A14: =IF('Master Tracker'!A45="","",'Master Tracker'!A45) -> ☐ | B14: =IF('Master Tracker'!B45="","",'Master Tracker'!B45) -> T-040 | C14: =IF('Master Tracker'!C45="","",'Master Tracker'!C45) -> Operations | D14: =IF('Master Tracker'!D45="","",'Master Tracker'!D45) -> Orders | E14: =IF('Master Tracker'!E45="","",'Master Tracker'!E45) -> Create manual order import fallback process | F14: =IF('Master Tracker'!F45="","",'Master Tracker'!F45) -> CSV/manual upload when API is unavailable | G14: =IF('Master Tracker'!G45="","",'Master Tracker'!G45) -> All | H14: =IF('Master Tracker'!H45="","",'Master Tracker'!H45) -> Medium | ... N14: =IF('Master Tracker'!N45="","",'Master Tracker'!N45)
A15: =IF('Master Tracker'!A46="","",'Master Tracker'!A46) -> ☐ | B15: =IF('Master Tracker'!B46="","",'Master Tracker'!B46) -> T-041 | C15: =IF('Master Tracker'!C46="","",'Master Tracker'!C46) -> Operations | D15: =IF('Master Tracker'!D46="","",'Master Tracker'!D46) -> Orders | E15: =IF('Master Tracker'!E46="","",'Master Tracker'!E46) -> Define order reconciliation process | F15: =IF('Master Tracker'!F46="","",'Master Tracker'!F46) -> Validate order count, distance, earnings and rider mapping against aggregator data | G15: =IF('Master Tracker'!G46="","",'Master Tracker'!G46) -> All | H15: =IF('Master Tracker'!H46="","",'Master Tracker'!H46) -> Critical | ... N15: =IF('Master Tracker'!N46="","",'Master Tracker'!N46)
A16: =IF('Master Tracker'!A47="","",'Master Tracker'!A47) -> ☐ | B16: =IF('Master Tracker'!B47="","",'Master Tracker'!B47) -> T-042 | C16: =IF('Master Tracker'!C47="","",'Master Tracker'!C47) -> Operations | D16: =IF('Master Tracker'!D47="","",'Master Tracker'!D47) -> Orders | E16: =IF('Master Tracker'!E47="","",'Master Tracker'!E47) -> Build exception queue for unassigned or mismatched orders | F16: =IF('Master Tracker'!F47="","",'Master Tracker'!F47) -> Surface issues where order, rider or vehicle mapping fails | G16: =IF('Master Tracker'!G47="","",'Master Tracker'!G47) -> All | H16: =IF('Master Tracker'!H47="","",'Master Tracker'!H47) -> High | ... N16: =IF('Master Tracker'!N47="","",'Master Tracker'!N47)
A17: =IF('Master Tracker'!A48="","",'Master Tracker'!A48) -> ☐ | B17: =IF('Master Tracker'!B48="","",'Master Tracker'!B48) -> T-043 | C17: =IF('Master Tracker'!C48="","",'Master Tracker'!C48) -> Operations | D17: =IF('Master Tracker'!D48="","",'Master Tracker'!D48) -> Incidents | E17: =IF('Master Tracker'!E48="","",'Master Tracker'!E48) -> Define accident / incident operating procedure | F17: =IF('Master Tracker'!F48="","",'Master Tracker'!F48) -> Who escalates, who approves, what evidence is required | G17: =IF('Master Tracker'!G48="","",'Master Tracker'!G48) -> All | H17: =IF('Master Tracker'!H48="","",'Master Tracker'!H48) -> High | ... N17: =IF('Master Tracker'!N48="","",'Master Tracker'!N48)
A18: =IF('Master Tracker'!A49="","",'Master Tracker'!A49) -> ☐ | B18: =IF('Master Tracker'!B49="","",'Master Tracker'!B49) -> T-044 | C18: =IF('Master Tracker'!C49="","",'Master Tracker'!C49) -> Operations | D18: =IF('Master Tracker'!D49="","",'Master Tracker'!D49) -> Resources | E18: =IF('Master Tracker'!E49="","",'Master Tracker'!E49) -> Define spare / replacement vehicle dispatch logic | F18: =IF('Master Tracker'!F49="","",'Master Tracker'!F49) -> How fast replacement happens and who is eligible | G18: =IF('Master Tracker'!G49="","",'Master Tracker'!G49) -> Owned + Rented | H18: =IF('Master Tracker'!H49="","",'Master Tracker'!H49) -> High | ... N18: =IF('Master Tracker'!N49="","",'Master Tracker'!N49)
A19: =IF('Master Tracker'!A50="","",'Master Tracker'!A50) -> ☐ | B19: =IF('Master Tracker'!B50="","",'Master Tracker'!B50) -> T-045 | C19: =IF('Master Tracker'!C50="","",'Master Tracker'!C50) -> Operations | D19: =IF('Master Tracker'!D50="","",'Master Tracker'!D50) -> Resources | E19: =IF('Master Tracker'!E50="","",'Master Tracker'!E50) -> Create rider-owned breakdown support policy | F19: =IF('Master Tracker'!F50="","",'Master Tracker'!F50) -> Clarify when the company helps and when the rider remains responsible | G19: =IF('Master Tracker'!G50="","",'Master Tracker'!G50) -> Rider-Owned Only | H19: =IF('Master Tracker'!H50="","",'Master Tracker'!H50) -> Medium | ... N19: =IF('Master Tracker'!N50="","",'Master Tracker'!N50)
A20: =IF('Master Tracker'!A51="","",'Master Tracker'!A51) -> ☐ | B20: =IF('Master Tracker'!B51="","",'Master Tracker'!B51) -> T-046 | C20: =IF('Master Tracker'!C51="","",'Master Tracker'!C51) -> Operations | D20: =IF('Master Tracker'!D51="","",'Master Tracker'!D51) -> Dashboard | E20: =IF('Master Tracker'!E51="","",'Master Tracker'!E51) -> Define operations dashboard metrics | F20: =IF('Master Tracker'!F51="","",'Master Tracker'!F51) -> Orders per rider, late deliveries, attendance gaps and downtime | G20: =IF('Master Tracker'!G51="","",'Master Tracker'!G51) -> All | H20: =IF('Master Tracker'!H51="","",'Master Tracker'!H51) -> Medium | ... N20: =IF('Master Tracker'!N51="","",'Master Tracker'!N51)

Sheet Fleet
A1: Fleet Checklist
A2: Linked departmental view for Fleet. Edit the Master Tracker tab as the source of truth; this tab mirrors those rows for focused review.
A5: Checklist | B5: Task ID | C5: Module | D5: Workstream | E5: Task | F5: Deliverable / Logic | G5: Source Type Impact | H5: Priority | I5: Phase | J5: Dependency | K5: Status | L5: Owner | M5: Target Date | N5: Notes
A6: =IF('Master Tracker'!A52="","",'Master Tracker'!A52) -> ☐ | B6: =IF('Master Tracker'!B52="","",'Master Tracker'!B52) -> T-047 | C6: =IF('Master Tracker'!C52="","",'Master Tracker'!C52) -> Fleet | D6: =IF('Master Tracker'!D52="","",'Master Tracker'!D52) -> Vehicle Master | E6: =IF('Master Tracker'!E52="","",'Master Tracker'!E52) -> Define vehicle onboarding checklist | F6: =IF('Master Tracker'!F52="","",'Master Tracker'!F52) -> Registration, insurance, photos, VIN/chassis and readiness check | G6: =IF('Master Tracker'!G52="","",'Master Tracker'!G52) -> All | H6: =IF('Master Tracker'!H52="","",'Master Tracker'!H52) -> Critical | ... N6: =IF('Master Tracker'!N52="","",'Master Tracker'!N52)
A7: =IF('Master Tracker'!A53="","",'Master Tracker'!A53) -> ☐ | B7: =IF('Master Tracker'!B53="","",'Master Tracker'!B53) -> T-048 | C7: =IF('Master Tracker'!C53="","",'Master Tracker'!C53) -> Fleet | D7: =IF('Master Tracker'!D53="","",'Master Tracker'!D53) -> Vehicle Master | E7: =IF('Master Tracker'!E53="","",'Master Tracker'!E53) -> Create source-type-specific field requirements | F7: =IF('Master Tracker'!F53="","",'Master Tracker'!F53) -> Owned purchase data, rental contract data, rider ownership proof | G7: =IF('Master Tracker'!G53="","",'Master Tracker'!G53) -> All (varies by source type) | H7: =IF('Master Tracker'!H53="","",'Master Tracker'!H53) -> Critical | ... N7: =IF('Master Tracker'!N53="","",'Master Tracker'!N53)
A8: =IF('Master Tracker'!A54="","",'Master Tracker'!A54) -> ☐ | B8: =IF('Master Tracker'!B54="","",'Master Tracker'!B54) -> T-049 | C8: =IF('Master Tracker'!C54="","",'Master Tracker'!C54) -> Fleet | D8: =IF('Master Tracker'!D54="","",'Master Tracker'!D54) -> Vehicle Master | E8: =IF('Master Tracker'!E54="","",'Master Tracker'!E54) -> Design supplier master for rented vehicles | F8: =IF('Master Tracker'!F54="","",'Master Tracker'!F54) -> Supplier contacts, contracts, rates, replacement terms and SLA | G8: =IF('Master Tracker'!G54="","",'Master Tracker'!G54) -> Rented Only | H8: =IF('Master Tracker'!H54="","",'Master Tracker'!H54) -> High | ... N8: =IF('Master Tracker'!N54="","",'Master Tracker'!N54)
A9: =IF('Master Tracker'!A55="","",'Master Tracker'!A55) -> ☐ | B9: =IF('Master Tracker'!B55="","",'Master Tracker'!B55) -> T-050 | C9: =IF('Master Tracker'!C55="","",'Master Tracker'!C55) -> Fleet | D9: =IF('Master Tracker'!D55="","",'Master Tracker'!D55) -> Vehicle Master | E9: =IF('Master Tracker'!E55="","",'Master Tracker'!E55) -> Design owned fleet asset profile | F9: =IF('Master Tracker'!F55="","",'Master Tracker'!F55) -> Purchase date, capex, expected life and disposal method | G9: =IF('Master Tracker'!G55="","",'Master Tracker'!G55) -> Owned Only | H9: =IF('Master Tracker'!H55="","",'Master Tracker'!H55) -> High | ... N9: =IF('Master Tracker'!N55="","",'Master Tracker'!N55)
A10: =IF('Master Tracker'!A56="","",'Master Tracker'!A56) -> ☐ | B10: =IF('Master Tracker'!B56="","",'Master Tracker'!B56) -> T-051 | C10: =IF('Master Tracker'!C56="","",'Master Tracker'!C56) -> Fleet | D10: =IF('Master Tracker'!D56="","",'Master Tracker'!D56) -> Vehicle Master | E10: =IF('Master Tracker'!E56="","",'Master Tracker'!E56) -> Design rider-owned approval workflow | F10: =IF('Master Tracker'!F56="","",'Master Tracker'!F56) -> Ownership proof, inspection, insurance and registration validation | G10: =IF('Master Tracker'!G56="","",'Master Tracker'!G56) -> Rider-Owned Only | H10: =IF('Master Tracker'!H56="","",'Master Tracker'!H56) -> Critical | ... N10: =IF('Master Tracker'!N56="","",'Master Tracker'!N56)
A11: =IF('Master Tracker'!A57="","",'Master Tracker'!A57) -> ☐ | B11: =IF('Master Tracker'!B57="","",'Master Tracker'!B57) -> T-052 | C11: =IF('Master Tracker'!C57="","",'Master Tracker'!C57) -> Fleet | D11: =IF('Master Tracker'!D57="","",'Master Tracker'!D57) -> Assignments | E11: =IF('Master Tracker'!E57="","",'Master Tracker'!E57) -> Implement vehicle assignment history and return flow | F11: =IF('Master Tracker'!F57="","",'Master Tracker'!F57) -> Track every assignment, off-hire, replacement and return | G11: =IF('Master Tracker'!G57="","",'Master Tracker'!G57) -> All | H11: =IF('Master Tracker'!H57="","",'Master Tracker'!H57) -> Critical | ... N11: =IF('Master Tracker'!N57="","",'Master Tracker'!N57)
A12: =IF('Master Tracker'!A58="","",'Master Tracker'!A58) -> ☐ | B12: =IF('Master Tracker'!B58="","",'Master Tracker'!B58) -> T-053 | C12: =IF('Master Tracker'!C58="","",'Master Tracker'!C58) -> Fleet | D12: =IF('Master Tracker'!D58="","",'Master Tracker'!D58) -> Assignments | E12: =IF('Master Tracker'!E58="","",'Master Tracker'!E58) -> Create vehicle handover checklist | F12: =IF('Master Tracker'!F58="","",'Master Tracker'!F58) -> Condition, accessories, damages, odometer and acknowledgment | G12: =IF('Master Tracker'!G58="","",'Master Tracker'!G58) -> Owned + Rented | H12: =IF('Master Tracker'!H58="","",'Master Tracker'!H58) -> High | ... N12: =IF('Master Tracker'!N58="","",'Master Tracker'!N58)
A13: =IF('Master Tracker'!A59="","",'Master Tracker'!A59) -> ☐ | B13: =IF('Master Tracker'!B59="","",'Master Tracker'!B59) -> T-054 | C13: =IF('Master Tracker'!C59="","",'Master Tracker'!C59) -> Fleet | D13: =IF('Master Tracker'!D59="","",'Master Tracker'!D59) -> Maintenance | E13: =IF('Master Tracker'!E59="","",'Master Tracker'!E59) -> Define preventive maintenance schedule | F13: =IF('Master Tracker'!F59="","",'Master Tracker'!F59) -> Service intervals by km/time for company-controlled vehicles | G13: =IF('Master Tracker'!G59="","",'Master Tracker'!G59) -> Owned + Rented | H13: =IF('Master Tracker'!H59="","",'Master Tracker'!H59) -> High | ... N13: =IF('Master Tracker'!N59="","",'Master Tracker'!N59)
A14: =IF('Master Tracker'!A60="","",'Master Tracker'!A60) -> ☐ | B14: =IF('Master Tracker'!B60="","",'Master Tracker'!B60) -> T-055 | C14: =IF('Master Tracker'!C60="","",'Master Tracker'!C60) -> Fleet | D14: =IF('Master Tracker'!D60="","",'Master Tracker'!D60) -> Maintenance | E14: =IF('Master Tracker'!E60="","",'Master Tracker'!E60) -> Define maintenance routing rules by source type | F14: =IF('Master Tracker'!F60="","",'Master Tracker'!F60) -> Supplier, internal workshop or rider responsibility | G14: =IF('Master Tracker'!G60="","",'Master Tracker'!G60) -> All (varies by source type) | H14: =IF('Master Tracker'!H60="","",'Master Tracker'!H60) -> Critical | ... N14: =IF('Master Tracker'!N60="","",'Master Tracker'!N60)
A15: =IF('Master Tracker'!A61="","",'Master Tracker'!A61) -> ☐ | B15: =IF('Master Tracker'!B61="","",'Master Tracker'!B61) -> T-056 | C15: =IF('Master Tracker'!C61="","",'Master Tracker'!C61) -> Fleet | D15: =IF('Master Tracker'!D61="","",'Master Tracker'!D61) -> Maintenance | E15: =IF('Master Tracker'!E61="","",'Master Tracker'!E61) -> Capture downtime start/end and replacement requirement | F15: =IF('Master Tracker'!F61="","",'Master Tracker'!F61) -> Feed utilization and loss analysis | G15: =IF('Master Tracker'!G61="","",'Master Tracker'!G61) -> All | H15: =IF('Master Tracker'!H61="","",'Master Tracker'!H61) -> High | ... N15: =IF('Master Tracker'!N61="","",'Master Tracker'!N61)
A16: =IF('Master Tracker'!A62="","",'Master Tracker'!A62) -> ☐ | B16: =IF('Master Tracker'!B62="","",'Master Tracker'!B62) -> T-057 | C16: =IF('Master Tracker'!C62="","",'Master Tracker'!C62) -> Fleet | D16: =IF('Master Tracker'!D62="","",'Master Tracker'!D62) -> Compliance | E16: =IF('Master Tracker'!E62="","",'Master Tracker'!E62) -> Create registration / insurance / inspection expiry tracker | F16: =IF('Master Tracker'!F62="","",'Master Tracker'!F62) -> Block usage of non-compliant vehicles | G16: =IF('Master Tracker'!G62="","",'Master Tracker'!G62) -> All | H16: =IF('Master Tracker'!H62="","",'Master Tracker'!H62) -> Critical | ... N16: =IF('Master Tracker'!N62="","",'Master Tracker'!N62)
A17: =IF('Master Tracker'!A63="","",'Master Tracker'!A63) -> ☐ | B17: =IF('Master Tracker'!B63="","",'Master Tracker'!B63) -> T-058 | C17: =IF('Master Tracker'!C63="","",'Master Tracker'!C63) -> Fleet | D17: =IF('Master Tracker'!D63="","",'Master Tracker'!D63) -> Compliance | E17: =IF('Master Tracker'!E63="","",'Master Tracker'!E63) -> Create return-to-supplier workflow for rented vehicles | F17: =IF('Master Tracker'!F63="","",'Master Tracker'!F63) -> Off-hire, condition check, penalties and closure | G17: =IF('Master Tracker'!G63="","",'Master Tracker'!G63) -> Rented Only | H17: =IF('Master Tracker'!H63="","",'Master Tracker'!H63) -> Medium | ... N17: =IF('Master Tracker'!N63="","",'Master Tracker'!N63)
... A20: =IF('Master Tracker'!A66="","",'Master Tracker'!A66) -> ☐ | B20: =IF('Master Tracker'!B66="","",'Master Tracker'!B66) -> T-061 | C20: =IF('Master Tracker'!C66="","",'Master Tracker'!C66) -> Fleet | D20: =IF('Master Tracker'!D66="","",'Master Tracker'!D66) -> Dashboard | E20: =IF('Master Tracker'!E66="","",'Master Tracker'!E66) -> Define fleet dashboard metrics | F20: =IF('Master Tracker'!F66="","",'Master Tracker'!F66) -> Utilization, downtime, aging, maintenance due and off-road count | G20: =IF('Master Tracker'!G66="","",'Master Tracker'!G66) -> All | H20: =IF('Master Tracker'!H66="","",'Master Tracker'!H66) -> Medium | ... N20: =IF('Master Tracker'!N66="","",'Master Tracker'!N66)

Sheet Finance
A1: Finance Checklist
A2: Linked departmental view for Finance. Edit the Master Tracker tab as the source of truth; this tab mirrors those rows for focused review.
A5: Checklist | B5: Task ID | C5: Module | D5: Workstream | E5: Task | F5: Deliverable / Logic | G5: Source Type Impact | H5: Priority | I5: Phase | J5: Dependency | K5: Status | L5: Owner | M5: Target Date | N5: Notes
A6: =IF('Master Tracker'!A67="","",'Master Tracker'!A67) -> ☐ | B6: =IF('Master Tracker'!B67="","",'Master Tracker'!B67) -> T-062 | C6: =IF('Master Tracker'!C67="","",'Master Tracker'!C67) -> Finance | D6: =IF('Master Tracker'!D67="","",'Master Tracker'!D67) -> Commercial Model | E6: =IF('Master Tracker'!E67="","",'Master Tracker'!E67) -> Map revenue models by aggregator and contract | F6: =IF('Master Tracker'!F67="","",'Master Tracker'!F67) -> Per order, hybrid, incentives, penalties and billing cycle | G6: =IF('Master Tracker'!G67="","",'Master Tracker'!G67) -> All | H6: =IF('Master Tracker'!H67="","",'Master Tracker'!H67) -> Critical | ... N6: =IF('Master Tracker'!N67="","",'Master Tracker'!N67)
A7: =IF('Master Tracker'!A68="","",'Master Tracker'!A68) -> ☐ | B7: =IF('Master Tracker'!B68="","",'Master Tracker'!B68) -> T-063 | C7: =IF('Master Tracker'!C68="","",'Master Tracker'!C68) -> Finance | D7: =IF('Master Tracker'!D68="","",'Master Tracker'!D68) -> Commercial Model | E7: =IF('Master Tracker'!E68="","",'Master Tracker'!E68) -> Design client / aggregator billing rules | F7: =IF('Master Tracker'!F68="","",'Master Tracker'!F68) -> Who gets billed, at what rate and under what reconciliation logic | G7: =IF('Master Tracker'!G68="","",'Master Tracker'!G68) -> All | H7: =IF('Master Tracker'!H68="","",'Master Tracker'!H68) -> Critical | ... N7: =IF('Master Tracker'!N68="","",'Master Tracker'!N68)
A8: =IF('Master Tracker'!A69="","",'Master Tracker'!A69) -> ☐ | B8: =IF('Master Tracker'!B69="","",'Master Tracker'!B69) -> T-064 | C8: =IF('Master Tracker'!C69="","",'Master Tracker'!C69) -> Finance | D8: =IF('Master Tracker'!D69="","",'Master Tracker'!D69) -> Cost Model | E8: =IF('Master Tracker'!E69="","",'Master Tracker'!E69) -> Build rented vehicle monthly cost model | F8: =IF('Master Tracker'!F69="","",'Master Tracker'!F69) -> Rent, deposit, insurance share, uncovered repairs and downtime cost | G8: =IF('Master Tracker'!G69="","",'Master Tracker'!G69) -> Rented Only | H8: =IF('Master Tracker'!H69="","",'Master Tracker'!H69) -> Critical | ... N8: =IF('Master Tracker'!N69="","",'Master Tracker'!N69)
A9: =IF('Master Tracker'!A70="","",'Master Tracker'!A70) -> ☐ | B9: =IF('Master Tracker'!B70="","",'Master Tracker'!B70) -> T-065 | C9: =IF('Master Tracker'!C70="","",'Master Tracker'!C70) -> Finance | D9: =IF('Master Tracker'!D70="","",'Master Tracker'!D70) -> Cost Model | E9: =IF('Master Tracker'!E70="","",'Master Tracker'!E70) -> Build owned vehicle monthly cost model | F9: =IF('Master Tracker'!F70="","",'Master Tracker'!F70) -> Depreciation, insurance, registration, maintenance and downtime | G9: =IF('Master Tracker'!G70="","",'Master Tracker'!G70) -> Owned Only | H9: =IF('Master Tracker'!H70="","",'Master Tracker'!H70) -> Critical | ... N9: =IF('Master Tracker'!N70="","",'Master Tracker'!N70)
A10: =IF('Master Tracker'!A71="","",'Master Tracker'!A71) -> ☐ | B10: =IF('Master Tracker'!B71="","",'Master Tracker'!B71) -> T-066 | C10: =IF('Master Tracker'!C71="","",'Master Tracker'!C71) -> Finance | D10: =IF('Master Tracker'!D71="","",'Master Tracker'!D71) -> Cost Model | E10: =IF('Master Tracker'!E71="","",'Master Tracker'!E71) -> Build rider-owned company cost model | F10: =IF('Master Tracker'!F71="","",'Master Tracker'!F71) -> Allowance, subsidy, compliance admin and support cost | G10: =IF('Master Tracker'!G71="","",'Master Tracker'!G71) -> Rider-Owned Only | H10: =IF('Master Tracker'!H71="","",'Master Tracker'!H71) -> High | ... N10: =IF('Master Tracker'!N71="","",'Master Tracker'!N71)
A11: =IF('Master Tracker'!A72="","",'Master Tracker'!A72) -> ☐ | B11: =IF('Master Tracker'!B72="","",'Master Tracker'!B72) -> T-067 | C11: =IF('Master Tracker'!C72="","",'Master Tracker'!C72) -> Finance | D11: =IF('Master Tracker'!D72="","",'Master Tracker'!D72) -> Payroll | E11: =IF('Master Tracker'!E72="","",'Master Tracker'!E72) -> Design payroll engine formula library | F11: =IF('Master Tracker'!F72="","",'Master Tracker'!F72) -> Fixed pay, per-order pay, km pay, incentive, deduction and advance recovery | G11: =IF('Master Tracker'!G72="","",'Master Tracker'!G72) -> All (varies by source type) | H11: =IF('Master Tracker'!H72="","",'Master Tracker'!H72) -> Critical | ... N11: =IF('Master Tracker'!N72="","",'Master Tracker'!N72)
A12: =IF('Master Tracker'!A73="","",'Master Tracker'!A73) -> ☐ | B12: =IF('Master Tracker'!B73="","",'Master Tracker'!B73) -> T-068 | C12: =IF('Master Tracker'!C73="","",'Master Tracker'!C73) -> Finance | D12: =IF('Master Tracker'!D73="","",'Master Tracker'!D73) -> Payroll | E12: =IF('Master Tracker'!E73="","",'Master Tracker'!E73) -> Map vehicle-related deductions and allowances | F12: =IF('Master Tracker'!F73="","",'Master Tracker'!F73) -> Different payroll treatment by vehicle source type | G12: =IF('Master Tracker'!G73="","",'Master Tracker'!G73) -> All (varies by source type) | H12: =IF('Master Tracker'!H73="","",'Master Tracker'!H73) -> Critical | ... N12: =IF('Master Tracker'!N73="","",'Master Tracker'!N73)
A13: =IF('Master Tracker'!A74="","",'Master Tracker'!A74) -> ☐ | B13: =IF('Master Tracker'!B74="","",'Master Tracker'!B74) -> T-069 | C13: =IF('Master Tracker'!C74="","",'Master Tracker'!C74) -> Finance | D13: =IF('Master Tracker'!D74="","",'Master Tracker'!D74) -> Payables | E13: =IF('Master Tracker'!E74="","",'Master Tracker'!E74) -> Build supplier rental payable workflow | F13: =IF('Master Tracker'!F74="","",'Master Tracker'!F74) -> Rental invoice intake, matching, approval and payment schedule | G13: =IF('Master Tracker'!G74="","",'Master Tracker'!G74) -> Rented Only | H13: =IF('Master Tracker'!H74="","",'Master Tracker'!H74) -> High | ... N13: =IF('Master Tracker'!N74="","",'Master Tracker'!N74)
A14: =IF('Master Tracker'!A75="","",'Master Tracker'!A75) -> ☐ | B14: =IF('Master Tracker'!B75="","",'Master Tracker'!B75) -> T-070 | C14: =IF('Master Tracker'!C75="","",'Master Tracker'!C75) -> Finance | D14: =IF('Master Tracker'!D75="","",'Master Tracker'!D75) -> Assets | E14: =IF('Master Tracker'!E75="","",'Master Tracker'!E75) -> Build depreciation schedule for owned fleet | F14: =IF('Master Tracker'!F75="","",'Master Tracker'!F75) -> Monthly depreciation and asset book value movement | G14: =IF('Master Tracker'!G75="","",'Master Tracker'!G75) -> Owned Only | H14: =IF('Master Tracker'!H75="","",'Master Tracker'!H75) -> High | ... N14: =IF('Master Tracker'!N75="","",'Master Tracker'!N75)
A15: =IF('Master Tracker'!A76="","",'Master Tracker'!A76) -> ☐ | B15: =IF('Master Tracker'!B76="","",'Master Tracker'!B76) -> T-071 | C15: =IF('Master Tracker'!C76="","",'Master Tracker'!C76) -> Finance | D15: =IF('Master Tracker'!D76="","",'Master Tracker'!D76) -> Receivables | E15: =IF('Master Tracker'!E76="","",'Master Tracker'!E76) -> Build invoicing workflow | F15: =IF('Master Tracker'!F76="","",'Master Tracker'!F76) -> Billing output by period, client, aggregator and supporting detail | G15: =IF('Master Tracker'!G76="","",'Master Tracker'!G76) -> All | H15: =IF('Master Tracker'!H76="","",'Master Tracker'!H76) -> High | ... N15: =IF('Master Tracker'!N76="","",'Master Tracker'!N76)
A16: =IF('Master Tracker'!A77="","",'Master Tracker'!A77) -> ☐ | B16: =IF('Master Tracker'!B77="","",'Master Tracker'!B77) -> T-072 | C16: =IF('Master Tracker'!C77="","",'Master Tracker'!C77) -> Finance | D16: =IF('Master Tracker'!D77="","",'Master Tracker'!D77) -> Receivables | E16: =IF('Master Tracker'!E77="","",'Master Tracker'!E77) -> Build collections and dispute tracker | F16: =IF('Master Tracker'!F77="","",'Master Tracker'!F77) -> Invoice aging, rejections and underpayment resolution | G16: =IF('Master Tracker'!G77="","",'Master Tracker'!G77) -> All | H16: =IF('Master Tracker'!H77="","",'Master Tracker'!H77) -> Medium | ... N16: =IF('Master Tracker'!N77="","",'Master Tracker'!N77)
A17: =IF('Master Tracker'!A78="","",'Master Tracker'!A78) -> ☐ | B17: =IF('Master Tracker'!B78="","",'Master Tracker'!B78) -> T-073 | C17: =IF('Master Tracker'!C78="","",'Master Tracker'!C78) -> Finance | D17: =IF('Master Tracker'!D78="","",'Master Tracker'!D78) -> Reporting | E17: =IF('Master Tracker'!E78="","",'Master Tracker'!E78) -> Define profit by vehicle source type report | F17: =IF('Master Tracker'!F78="","",'Master Tracker'!F78) -> Owned vs rented vs rider-owned profitability | G17: =IF('Master Tracker'!G78="","",'Master Tracker'!G78) -> All | H17: =IF('Master Tracker'!H78="","",'Master Tracker'!H78) -> Critical | ... N17: =IF('Master Tracker'!N78="","",'Master Tracker'!N78)
... A20: =IF('Master Tracker'!A81="","",'Master Tracker'!A81) -> ☐ | B20: =IF('Master Tracker'!B81="","",'Master Tracker'!B81) -> T-076 | C20: =IF('Master Tracker'!C81="","",'Master Tracker'!C81) -> Finance | D20: =IF('Master Tracker'!D81="","",'Master Tracker'!D81) -> Dashboard | E20: =IF('Master Tracker'!E81="","",'Master Tracker'!E81) -> Define finance dashboard metrics | F20: =IF('Master Tracker'!F81="","",'Master Tracker'!F81) -> Revenue, gross margin, cost per delivery, payables and receivables | G20: =IF('Master Tracker'!G81="","",'Master Tracker'!G81) -> All | H20: =IF('Master Tracker'!H81="","",'Master Tracker'!H81) -> Medium | ... N20: =IF('Master Tracker'!N81="","",'Master Tracker'!N81)

Sheet Compliance
A1: Compliance Checklist
A2: Linked departmental view for Compliance. Edit the Master Tracker tab as the source of truth; this tab mirrors those rows for focused review.
A5: Checklist | B5: Task ID | C5: Module | D5: Workstream | E5: Task | F5: Deliverable / Logic | G5: Source Type Impact | H5: Priority | I5: Phase | J5: Dependency | K5: Status | L5: Owner | M5: Target Date | N5: Notes
A6: =IF('Master Tracker'!A82="","",'Master Tracker'!A82) -> ☐ | B6: =IF('Master Tracker'!B82="","",'Master Tracker'!B82) -> T-077 | C6: =IF('Master Tracker'!C82="","",'Master Tracker'!C82) -> Compliance | D6: =IF('Master Tracker'!D82="","",'Master Tracker'!D82) -> Policy Matrix | E6: =IF('Master Tracker'!E82="","",'Master Tracker'!E82) -> Create legal and compliance document matrix | F6: =IF('Master Tracker'!F82="","",'Master Tracker'!F82) -> List mandatory rider and vehicle documents by country / client / aggregator | G6: =IF('Master Tracker'!G82="","",'Master Tracker'!G82) -> All | H6: =IF('Master Tracker'!H82="","",'Master Tracker'!H82) -> Critical | ... N6: =IF('Master Tracker'!N82="","",'Master Tracker'!N82)
A7: =IF('Master Tracker'!A83="","",'Master Tracker'!A83) -> ☐ | B7: =IF('Master Tracker'!B83="","",'Master Tracker'!B83) -> T-078 | C7: =IF('Master Tracker'!C83="","",'Master Tracker'!C83) -> Compliance | D7: =IF('Master Tracker'!D83="","",'Master Tracker'!D83) -> Activation Controls | E7: =IF('Master Tracker'!E83="","",'Master Tracker'!E83) -> Create rider activation block rules | F7: =IF('Master Tracker'!F83="","",'Master Tracker'!F83) -> Stop activation for expired visa, license or invalid bank / contract status | G7: =IF('Master Tracker'!G83="","",'Master Tracker'!G83) -> All | H7: =IF('Master Tracker'!H83="","",'Master Tracker'!H83) -> Critical | ... N7: =IF('Master Tracker'!N83="","",'Master Tracker'!N83)
A8: =IF('Master Tracker'!A84="","",'Master Tracker'!A84) -> ☐ | B8: =IF('Master Tracker'!B84="","",'Master Tracker'!B84) -> T-079 | C8: =IF('Master Tracker'!C84="","",'Master Tracker'!C84) -> Compliance | D8: =IF('Master Tracker'!D84="","",'Master Tracker'!D84) -> Activation Controls | E8: =IF('Master Tracker'!E84="","",'Master Tracker'!E84) -> Create vehicle activation block rules | F8: =IF('Master Tracker'!F84="","",'Master Tracker'!F84) -> Stop use for expired registration, insurance or failed inspection | G8: =IF('Master Tracker'!G84="","",'Master Tracker'!G84) -> All | H8: =IF('Master Tracker'!H84="","",'Master Tracker'!H84) -> Critical | ... N8: =IF('Master Tracker'!N84="","",'Master Tracker'!N84)
A9: =IF('Master Tracker'!A85="","",'Master Tracker'!A85) -> ☐ | B9: =IF('Master Tracker'!B85="","",'Master Tracker'!B85) -> T-080 | C9: =IF('Master Tracker'!C85="","",'Master Tracker'!C85) -> Compliance | D9: =IF('Master Tracker'!D85="","",'Master Tracker'!D85) -> Source-Type Controls | E9: =IF('Master Tracker'!E85="","",'Master Tracker'!E85) -> Define rider-owned vehicle approval controls | F9: =IF('Master Tracker'!F85="","",'Master Tracker'!F85) -> Proof of ownership, inspection, insurance and registration verification | G9: =IF('Master Tracker'!G85="","",'Master Tracker'!G85) -> Rider-Owned Only | H9: =IF('Master Tracker'!H85="","",'Master Tracker'!H85) -> Critical | ... N9: =IF('Master Tracker'!N85="","",'Master Tracker'!N85)
A10: =IF('Master Tracker'!A86="","",'Master Tracker'!A86) -> ☐ | B10: =IF('Master Tracker'!B86="","",'Master Tracker'!B86) -> T-081 | C10: =IF('Master Tracker'!C86="","",'Master Tracker'!C86) -> Compliance | D10: =IF('Master Tracker'!D86="","",'Master Tracker'!D86) -> Source-Type Controls | E10: =IF('Master Tracker'!E86="","",'Master Tracker'!E86) -> Define rented vehicle supplier control requirements | F10: =IF('Master Tracker'!F86="","",'Master Tracker'!F86) -> Valid contract, return terms, liability terms and SLA | G10: =IF('Master Tracker'!G86="","",'Master Tracker'!G86) -> Rented Only | H10: =IF('Master Tracker'!H86="","",'Master Tracker'!H86) -> High | ... N10: =IF('Master Tracker'!N86="","",'Master Tracker'!N86)
A11: =IF('Master Tracker'!A87="","",'Master Tracker'!A87) -> ☐ | B11: =IF('Master Tracker'!B87="","",'Master Tracker'!B87) -> T-082 | C11: =IF('Master Tracker'!C87="","",'Master Tracker'!C87) -> Compliance | D11: =IF('Master Tracker'!D87="","",'Master Tracker'!D87) -> Source-Type Controls | E11: =IF('Master Tracker'!E87="","",'Master Tracker'!E87) -> Define owned fleet audit requirements | F11: =IF('Master Tracker'!F87="","",'Master Tracker'!F87) -> Asset tag, depreciation setup and maintenance plan existence | G11: =IF('Master Tracker'!G87="","",'Master Tracker'!G87) -> Owned Only | H11: =IF('Master Tracker'!H87="","",'Master Tracker'!H87) -> Medium | ... N11: =IF('Master Tracker'!N87="","",'Master Tracker'!N87)
A12: =IF('Master Tracker'!A88="","",'Master Tracker'!A88) -> ☐ | B12: =IF('Master Tracker'!B88="","",'Master Tracker'!B88) -> T-083 | C12: =IF('Master Tracker'!C88="","",'Master Tracker'!C88) -> Compliance | D12: =IF('Master Tracker'!D88="","",'Master Tracker'!D88) -> Incidents | E12: =IF('Master Tracker'!E88="","",'Master Tracker'!E88) -> Create accident evidence checklist | F12: =IF('Master Tracker'!F88="","",'Master Tracker'!F88) -> Photos, police report, rider statement, vehicle status and recovery decision | G12: =IF('Master Tracker'!G88="","",'Master Tracker'!G88) -> All | H12: =IF('Master Tracker'!H88="","",'Master Tracker'!H88) -> High | ... N12: =IF('Master Tracker'!N88="","",'Master Tracker'!N88)
A13: =IF('Master Tracker'!A89="","",'Master Tracker'!A89) -> ☐ | B13: =IF('Master Tracker'!B89="","",'Master Tracker'!B89) -> T-084 | C13: =IF('Master Tracker'!C89="","",'Master Tracker'!C89) -> Compliance | D13: =IF('Master Tracker'!D89="","",'Master Tracker'!D89) -> Incidents | E13: =IF('Master Tracker'!E89="","",'Master Tracker'!E89) -> Create liability and recovery approval flow | F13: =IF('Master Tracker'!F89="","",'Master Tracker'!F89) -> Who decides cost recovery and what threshold requires finance approval | G13: =IF('Master Tracker'!G89="","",'Master Tracker'!G89) -> All (varies by source type) | H13: =IF('Master Tracker'!H89="","",'Master Tracker'!H89) -> High | ... N13: =IF('Master Tracker'!N89="","",'Master Tracker'!N89)
A14: =IF('Master Tracker'!A90="","",'Master Tracker'!A90) -> ☐ | B14: =IF('Master Tracker'!B90="","",'Master Tracker'!B90) -> T-085 | C14: =IF('Master Tracker'!C90="","",'Master Tracker'!C90) -> Compliance | D14: =IF('Master Tracker'!D90="","",'Master Tracker'!D90) -> Audit Trail | E14: =IF('Master Tracker'!E90="","",'Master Tracker'!E90) -> Define audit log requirements | F14: =IF('Master Tracker'!F90="","",'Master Tracker'!F90) -> Track who changed status, rates, assignments and payroll-sensitive fields | G14: =IF('Master Tracker'!G90="","",'Master Tracker'!G90) -> All | H14: =IF('Master Tracker'!H90="","",'Master Tracker'!H90) -> High | ... N14: =IF('Master Tracker'!N90="","",'Master Tracker'!N90)
A15: =IF('Master Tracker'!A91="","",'Master Tracker'!A91) -> ☐ | B15: =IF('Master Tracker'!B91="","",'Master Tracker'!B91) -> T-086 | C15: =IF('Master Tracker'!C91="","",'Master Tracker'!C91) -> Compliance | D15: =IF('Master Tracker'!D91="","",'Master Tracker'!D91) -> Approvals | E15: =IF('Master Tracker'!E91="","",'Master Tracker'!E91) -> Define exception approval workflow | F15: =IF('Master Tracker'!F91="","",'Master Tracker'!F91) -> Temporary overrides for urgent shifts, document grace periods or replacement use | G15: =IF('Master Tracker'!G91="","",'Master Tracker'!G91) -> All | H15: =IF('Master Tracker'!H91="","",'Master Tracker'!H91) -> High | ... N15: =IF('Master Tracker'!N91="","",'Master Tracker'!N91)
A16: =IF('Master Tracker'!A92="","",'Master Tracker'!A92) -> ☐ | B16: =IF('Master Tracker'!B92="","",'Master Tracker'!B92) -> T-087 | C16: =IF('Master Tracker'!C92="","",'Master Tracker'!C92) -> Compliance | D16: =IF('Master Tracker'!D92="","",'Master Tracker'!D92) -> Records | E16: =IF('Master Tracker'!E92="","",'Master Tracker'!E92) -> Define document archive and retention policy | F16: =IF('Master Tracker'!F92="","",'Master Tracker'!F92) -> Store rider docs, contracts, vehicle docs and supplier agreements | G16: =IF('Master Tracker'!G92="","",'Master Tracker'!G92) -> All | H16: =IF('Master Tracker'!H92="","",'Master Tracker'!H92) -> Medium | ... N16: =IF('Master Tracker'!N92="","",'Master Tracker'!N92)
A17: =IF('Master Tracker'!A93="","",'Master Tracker'!A93) -> ☐ | B17: =IF('Master Tracker'!B93="","",'Master Tracker'!B93) -> T-088 | C17: =IF('Master Tracker'!C93="","",'Master Tracker'!C93) -> Compliance | D17: =IF('Master Tracker'!D93="","",'Master Tracker'!D93) -> Dashboard | E17: =IF('Master Tracker'!E93="","",'Master Tracker'!E93) -> Define compliance dashboard metrics | F17: =IF('Master Tracker'!F93="","",'Master Tracker'!F93) -> Expired docs, blocked riders, blocked vehicles and open incidents | G17: =IF('Master Tracker'!G93="","",'Master Tracker'!G93) -> All | H17: =IF('Master Tracker'!H93="","",'Master Tracker'!H93) -> Medium | ... N17: =IF('Master Tracker'!N93="","",'Master Tracker'!N93)

Sheet Integrations
A1: Integrations Checklist
A2: Linked departmental view for Integrations. Edit the Master Tracker tab as the source of truth; this tab mirrors those rows for focused review.
A5: Checklist | B5: Task ID | C5: Module | D5: Workstream | E5: Task | F5: Deliverable / Logic | G5: Source Type Impact | H5: Priority | I5: Phase | J5: Dependency | K5: Status | L5: Owner | M5: Target Date | N5: Notes
A6: =IF('Master Tracker'!A94="","",'Master Tracker'!A94) -> ☐ | B6: =IF('Master Tracker'!B94="","",'Master Tracker'!B94) -> T-089 | C6: =IF('Master Tracker'!C94="","",'Master Tracker'!C94) -> Integrations | D6: =IF('Master Tracker'!D94="","",'Master Tracker'!D94) -> Aggregator APIs | E6: =IF('Master Tracker'!E94="","",'Master Tracker'!E94) -> Gather API requirements for Talabat / Jahez / Keeta | F6: =IF('Master Tracker'!F94="","",'Master Tracker'!F94) -> Auth method, order feed, rider mapping, earnings and reconciliation data | G6: =IF('Master Tracker'!G94="","",'Master Tracker'!G94) -> All | H6: =IF('Master Tracker'!H94="","",'Master Tracker'!H94) -> Critical | ... N6: =IF('Master Tracker'!N94="","",'Master Tracker'!N94)
A7: =IF('Master Tracker'!A95="","",'Master Tracker'!A95) -> ☐ | B7: =IF('Master Tracker'!B95="","",'Master Tracker'!B95) -> T-090 | C7: =IF('Master Tracker'!C95="","",'Master Tracker'!C95) -> Integrations | D7: =IF('Master Tracker'!D95="","",'Master Tracker'!D95) -> Aggregator APIs | E7: =IF('Master Tracker'!E95="","",'Master Tracker'!E95) -> Design external order ID mapping strategy | F7: =IF('Master Tracker'!F95="","",'Master Tracker'!F95) -> Persist unique order references and source import lineage | G7: =IF('Master Tracker'!G95="","",'Master Tracker'!G95) -> All | H7: =IF('Master Tracker'!H95="","",'Master Tracker'!H95) -> Critical | ... N7: =IF('Master Tracker'!N95="","",'Master Tracker'!N95)
A8: =IF('Master Tracker'!A96="","",'Master Tracker'!A96) -> ☐ | B8: =IF('Master Tracker'!B96="","",'Master Tracker'!B96) -> T-091 | C8: =IF('Master Tracker'!C96="","",'Master Tracker'!C96) -> Integrations | D8: =IF('Master Tracker'!D96="","",'Master Tracker'!D96) -> Aggregator APIs | E8: =IF('Master Tracker'!E96="","",'Master Tracker'!E96) -> Design earnings / incentive import mapping | F8: =IF('Master Tracker'!F96="","",'Master Tracker'!F96) -> Link imported payouts to payroll and billing calculations | G8: =IF('Master Tracker'!G96="","",'Master Tracker'!G96) -> All | H8: =IF('Master Tracker'!H96="","",'Master Tracker'!H96) -> High | ... N8: =IF('Master Tracker'!N96="","",'Master Tracker'!N96)
A9: =IF('Master Tracker'!A97="","",'Master Tracker'!A97) -> ☐ | B9: =IF('Master Tracker'!B97="","",'Master Tracker'!B97) -> T-092 | C9: =IF('Master Tracker'!C97="","",'Master Tracker'!C97) -> Integrations | D9: =IF('Master Tracker'!D97="","",'Master Tracker'!D97) -> Mobility | E9: =IF('Master Tracker'!E97="","",'Master Tracker'!E97) -> Define GPS / telematics integration requirements | F9: =IF('Master Tracker'!F97="","",'Master Tracker'!F97) -> Location, trip timing, speed, distance and route evidence | G9: =IF('Master Tracker'!G97="","",'Master Tracker'!G97) -> All | H9: =IF('Master Tracker'!H97="","",'Master Tracker'!H97) -> High | ... N9: =IF('Master Tracker'!N97="","",'Master Tracker'!N97)
A10: =IF('Master Tracker'!A98="","",'Master Tracker'!A98) -> ☐ | B10: =IF('Master Tracker'!B98="","",'Master Tracker'!B98) -> T-093 | C10: =IF('Master Tracker'!C98="","",'Master Tracker'!C98) -> Integrations | D10: =IF('Master Tracker'!D98="","",'Master Tracker'!D98) -> Mobility | E10: =IF('Master Tracker'!E98="","",'Master Tracker'!E98) -> Define mobile app needs for rider and supervisor | F10: =IF('Master Tracker'!F98="","",'Master Tracker'!F98) -> Attendance, issues, assignment view, earnings and compliance reminders | G10: =IF('Master Tracker'!G98="","",'Master Tracker'!G98) -> All | H10: =IF('Master Tracker'!H98="","",'Master Tracker'!H98) -> High | ... N10: =IF('Master Tracker'!N98="","",'Master Tracker'!N98)
A11: =IF('Master Tracker'!A99="","",'Master Tracker'!A99) -> ☐ | B11: =IF('Master Tracker'!B99="","",'Master Tracker'!B99) -> T-094 | C11: =IF('Master Tracker'!C99="","",'Master Tracker'!C99) -> Integrations | D11: =IF('Master Tracker'!D99="","",'Master Tracker'!D99) -> Finance Systems | E11: =IF('Master Tracker'!E99="","",'Master Tracker'!E99) -> Define accounting system integration scope | F11: =IF('Master Tracker'!F99="","",'Master Tracker'!F99) -> AP, AR, payroll journals, asset movements and cost centers | G11: =IF('Master Tracker'!G99="","",'Master Tracker'!G99) -> All | H11: =IF('Master Tracker'!H99="","",'Master Tracker'!H99) -> Medium | ... N11: =IF('Master Tracker'!N99="","",'Master Tracker'!N99)
A12: =IF('Master Tracker'!A100="","",'Master Tracker'!A100) -> ☐ | B12: =IF('Master Tracker'!B100="","",'Master Tracker'!B100) -> T-095 | C12: =IF('Master Tracker'!C100="","",'Master Tracker'!C100) -> Integrations | D12: =IF('Master Tracker'!D100="","",'Master Tracker'!D100) -> Documents | E12: =IF('Master Tracker'!E100="","",'Master Tracker'!E100) -> Define e-sign / document storage integration | F12: =IF('Master Tracker'!F100="","",'Master Tracker'!F100) -> Contracts, document uploads and approval evidence | G12: =IF('Master Tracker'!G100="","",'Master Tracker'!G100) -> All | H12: =IF('Master Tracker'!H100="","",'Master Tracker'!H100) -> Medium | ... N12: =IF('Master Tracker'!N100="","",'Master Tracker'!N100)
A13: =IF('Master Tracker'!A101="","",'Master Tracker'!A101) -> ☐ | B13: =IF('Master Tracker'!B101="","",'Master Tracker'!B101) -> T-096 | C13: =IF('Master Tracker'!C101="","",'Master Tracker'!C101) -> Integrations | D13: =IF('Master Tracker'!D101="","",'Master Tracker'!D101) -> Notifications | E13: =IF('Master Tracker'!E101="","",'Master Tracker'!E101) -> Create alerting requirements | F13: =IF('Master Tracker'!F101="","",'Master Tracker'!F101) -> Expiry alerts, breakdown alerts, blocked activation and payroll exceptions | G13: =IF('Master Tracker'!G101="","",'Master Tracker'!G101) -> All | H13: =IF('Master Tracker'!H101="","",'Master Tracker'!H101) -> High | ... N13: =IF('Master Tracker'!N101="","",'Master Tracker'!N101)
A14: =IF('Master Tracker'!A102="","",'Master Tracker'!A102) -> ☐ | B14: =IF('Master Tracker'!B102="","",'Master Tracker'!B102) -> T-097 | C14: =IF('Master Tracker'!C102="","",'Master Tracker'!C102) -> Integrations | D14: =IF('Master Tracker'!D102="","",'Master Tracker'!D102) -> Reliability | E14: =IF('Master Tracker'!E102="","",'Master Tracker'!E102) -> Design webhook retry and error handling | F14: =IF('Master Tracker'!F102="","",'Master Tracker'!F102) -> Ensure imports are idempotent, monitored and replayable | G14: =IF('Master Tracker'!G102="","",'Master Tracker'!G102) -> All | H14: =IF('Master Tracker'!H102="","",'Master Tracker'!H102) -> High | ... N14: =IF('Master Tracker'!N102="","",'Master Tracker'!N102)
A15: =IF('Master Tracker'!A103="","",'Master Tracker'!A103) -> ☐ | B15: =IF('Master Tracker'!B103="","",'Master Tracker'!B103) -> T-098 | C15: =IF('Master Tracker'!C103="","",'Master Tracker'!C103) -> Integrations | D15: =IF('Master Tracker'!D103="","",'Master Tracker'!D103) -> Reliability | E15: =IF('Master Tracker'!E103="","",'Master Tracker'!E103) -> Create integration monitoring checklist | F15: =IF('Master Tracker'!F103="","",'Master Tracker'!F103) -> Daily file/API status, failures, latency and reconciliation gaps | G15: =IF('Master Tracker'!G103="","",'Master Tracker'!G103) -> All | H15: =IF('Master Tracker'!H103="","",'Master Tracker'!H103) -> Medium | ... N15: =IF('Master Tracker'!N103="","",'Master Tracker'!N103)

Sheet BI & Reports
A1: BI & Reports Checklist
A2: Linked departmental view for BI & Reports. Edit the Master Tracker tab as the source of truth; this tab mirrors those rows for focused review.
A5: Checklist | B5: Task ID | C5: Module | D5: Workstream | E5: Task | F5: Deliverable / Logic | G5: Source Type Impact | H5: Priority | I5: Phase | J5: Dependency | K5: Status | L5: Owner | M5: Target Date | N5: Notes
A6: =IF('Master Tracker'!A104="","",'Master Tracker'!A104) -> ☐ | B6: =IF('Master Tracker'!B104="","",'Master Tracker'!B104) -> T-099 | C6: =IF('Master Tracker'!C104="","",'Master Tracker'!C104) -> BI & Reports | D6: =IF('Master Tracker'!D104="","",'Master Tracker'!D104) -> Metric Design | E6: =IF('Master Tracker'!E104="","",'Master Tracker'!E104) -> Create KPI dictionary | F6: =IF('Master Tracker'!F104="","",'Master Tracker'!F104) -> Define formulas, owners, grain and refresh frequency for each KPI | G6: =IF('Master Tracker'!G104="","",'Master Tracker'!G104) -> All | H6: =IF('Master Tracker'!H104="","",'Master Tracker'!H104) -> High | ... N6: =IF('Master Tracker'!N104="","",'Master Tracker'!N104)
A7: =IF('Master Tracker'!A105="","",'Master Tracker'!A105) -> ☐ | B7: =IF('Master Tracker'!B105="","",'Master Tracker'!B105) -> T-100 | C7: =IF('Master Tracker'!C105="","",'Master Tracker'!C105) -> BI & Reports | D7: =IF('Master Tracker'!D105="","",'Master Tracker'!D105) -> Metric Design | E7: =IF('Master Tracker'!E105="","",'Master Tracker'!E105) -> Define source-type profitability KPIs | F7: =IF('Master Tracker'!F105="","",'Master Tracker'!F105) -> Profit per owned / rented / rider-owned vehicle model | G7: =IF('Master Tracker'!G105="","",'Master Tracker'!G105) -> All | H7: =IF('Master Tracker'!H105="","",'Master Tracker'!H105) -> Critical | ... N7: =IF('Master Tracker'!N105="","",'Master Tracker'!N105)
A8: =IF('Master Tracker'!A106="","",'Master Tracker'!A106) -> ☐ | B8: =IF('Master Tracker'!B106="","",'Master Tracker'!B106) -> T-101 | C8: =IF('Master Tracker'!C106="","",'Master Tracker'!C106) -> BI & Reports | D8: =IF('Master Tracker'!D106="","",'Master Tracker'!D106) -> Executive Reports | E8: =IF('Master Tracker'!E106="","",'Master Tracker'!E106) -> Design CEO dashboard | F8: =IF('Master Tracker'!F106="","",'Master Tracker'!F106) -> Revenue, gross margin, active riders, source-type mix and risk counts | G8: =IF('Master Tracker'!G106="","",'Master Tracker'!G106) -> All | H8: =IF('Master Tracker'!H106="","",'Master Tracker'!H106) -> Medium | ... N8: =IF('Master Tracker'!N106="","",'Master Tracker'!N106)
A9: =IF('Master Tracker'!A107="","",'Master Tracker'!A107) -> ☐ | B9: =IF('Master Tracker'!B107="","",'Master Tracker'!B107) -> T-102 | C9: =IF('Master Tracker'!C107="","",'Master Tracker'!C107) -> BI & Reports | D9: =IF('Master Tracker'!D107="","",'Master Tracker'!D107) -> Executive Reports | E9: =IF('Master Tracker'!E107="","",'Master Tracker'!E107) -> Design weekly executive pack | F9: =IF('Master Tracker'!F107="","",'Master Tracker'!F107) -> Compact performance summary for leadership review | G9: =IF('Master Tracker'!G107="","",'Master Tracker'!G107) -> All | H9: =IF('Master Tracker'!H107="","",'Master Tracker'!H107) -> Low | ... N9: =IF('Master Tracker'!N107="","",'Master Tracker'!N107)
A10: =IF('Master Tracker'!A108="","",'Master Tracker'!A108) -> ☐ | B10: =IF('Master Tracker'!B108="","",'Master Tracker'!B108) -> T-103 | C10: =IF('Master Tracker'!C108="","",'Master Tracker'!C108) -> BI & Reports | D10: =IF('Master Tracker'!D108="","",'Master Tracker'!D108) -> Ops Reports | E10: =IF('Master Tracker'!E108="","",'Master Tracker'!E108) -> Define rider productivity report | F10: =IF('Master Tracker'!F108="","",'Master Tracker'!F108) -> Orders per rider, shift hours, acceptance and downtime impact | G10: =IF('Master Tracker'!G108="","",'Master Tracker'!G108) -> All | H10: =IF('Master Tracker'!H108="","",'Master Tracker'!H108) -> Medium | ... N10: =IF('Master Tracker'!N108="","",'Master Tracker'!N108)
A11: =IF('Master Tracker'!A109="","",'Master Tracker'!A109) -> ☐ | B11: =IF('Master Tracker'!B109="","",'Master Tracker'!B109) -> T-104 | C11: =IF('Master Tracker'!C109="","",'Master Tracker'!C109) -> BI & Reports | D11: =IF('Master Tracker'!D109="","",'Master Tracker'!D109) -> Ops Reports | E11: =IF('Master Tracker'!E109="","",'Master Tracker'!E109) -> Define idle rider / idle vehicle analysis | F11: =IF('Master Tracker'!F109="","",'Master Tracker'!F109) -> Find underutilized resources and pairing opportunities | G11: =IF('Master Tracker'!G109="","",'Master Tracker'!G109) -> Owned + Rented | H11: =IF('Master Tracker'!H109="","",'Master Tracker'!H109) -> Medium | ... N11: =IF('Master Tracker'!N109="","",'Master Tracker'!N109)
A12: =IF('Master Tracker'!A110="","",'Master Tracker'!A110) -> ☐ | B12: =IF('Master Tracker'!B110="","",'Master Tracker'!B110) -> T-105 | C12: =IF('Master Tracker'!C110="","",'Master Tracker'!C110) -> BI & Reports | D12: =IF('Master Tracker'!D110="","",'Master Tracker'!D110) -> Fleet Reports | E12: =IF('Master Tracker'!E110="","",'Master Tracker'!E110) -> Define fleet aging and replacement report | F12: =IF('Master Tracker'!F110="","",'Master Tracker'!F110) -> Owned fleet lifecycle and disposal signals | G12: =IF('Master Tracker'!G110="","",'Master Tracker'!G110) -> Owned Only | H12: =IF('Master Tracker'!H110="","",'Master Tracker'!H110) -> Medium | ... N12: =IF('Master Tracker'!N110="","",'Master Tracker'!N110)
A13: =IF('Master Tracker'!A111="","",'Master Tracker'!A111) -> ☐ | B13: =IF('Master Tracker'!B111="","",'Master Tracker'!B111) -> T-106 | C13: =IF('Master Tracker'!C111="","",'Master Tracker'!C111) -> BI & Reports | D13: =IF('Master Tracker'!D111="","",'Master Tracker'!D111) -> Fleet Reports | E13: =IF('Master Tracker'!E111="","",'Master Tracker'!E111) -> Define downtime and maintenance report | F13: =IF('Master Tracker'!F111="","",'Master Tracker'!F111) -> Events, hours lost, cause and replacement demand | G13: =IF('Master Tracker'!G111="","",'Master Tracker'!G111) -> All | H13: =IF('Master Tracker'!H111="","",'Master Tracker'!H111) -> Medium | ... N13: =IF('Master Tracker'!N111="","",'Master Tracker'!N111)
A14: =IF('Master Tracker'!A112="","",'Master Tracker'!A112) -> ☐ | B14: =IF('Master Tracker'!B112="","",'Master Tracker'!B112) -> T-107 | C14: =IF('Master Tracker'!C112="","",'Master Tracker'!C112) -> BI & Reports | D14: =IF('Master Tracker'!D112="","",'Master Tracker'!D112) -> Finance Reports | E14: =IF('Master Tracker'!E112="","",'Master Tracker'!E112) -> Define payroll exception report | F14: =IF('Master Tracker'!F112="","",'Master Tracker'!F112) -> Outliers in incentives, deductions, zero-pay and negative-pay cases | G14: =IF('Master Tracker'!G112="","",'Master Tracker'!G112) -> All | H14: =IF('Master Tracker'!H112="","",'Master Tracker'!H112) -> High | ... N14: =IF('Master Tracker'!N112="","",'Master Tracker'!N112)
A15: =IF('Master Tracker'!A113="","",'Master Tracker'!A113) -> ☐ | B15: =IF('Master Tracker'!B113="","",'Master Tracker'!B113) -> T-108 | C15: =IF('Master Tracker'!C113="","",'Master Tracker'!C113) -> BI & Reports | D15: =IF('Master Tracker'!D113="","",'Master Tracker'!D113) -> Finance Reports | E15: =IF('Master Tracker'!E113="","",'Master Tracker'!E113) -> Define billing reconciliation report | F15: =IF('Master Tracker'!F113="","",'Master Tracker'!F113) -> Order count, revenue, disputes and invoice support by period | G15: =IF('Master Tracker'!G113="","",'Master Tracker'!G113) -> All | H15: =IF('Master Tracker'!H113="","",'Master Tracker'!H113) -> High | ... N15: =IF('Master Tracker'!N113="","",'Master Tracker'!N113)
A16: =IF('Master Tracker'!A114="","",'Master Tracker'!A114) -> ☐ | B16: =IF('Master Tracker'!B114="","",'Master Tracker'!B114) -> T-109 | C16: =IF('Master Tracker'!C114="","",'Master Tracker'!C114) -> BI & Reports | D16: =IF('Master Tracker'!D114="","",'Master Tracker'!D114) -> Compliance Reports | E16: =IF('Master Tracker'!E114="","",'Master Tracker'!E114) -> Define compliance risk report | F16: =IF('Master Tracker'!F114="","",'Master Tracker'!F114) -> Upcoming expiries, blocked assets, blocked riders and unresolved incidents | G16: =IF('Master Tracker'!G114="","",'Master Tracker'!G114) -> All | H16: =IF('Master Tracker'!H114="","",'Master Tracker'!H114) -> Medium | ... N16: =IF('Master Tracker'!N114="","",'Master Tracker'!N114)

Sheet Logic Register
A1: Logic Register & Acceptance Checklist
A2: Lock these rules before development. Use this sheet for validation, UAT and change control.
A5: Rule ID | B5: Area | C5: Trigger / Event | D5: Expected System Behavior | E5: Source Type Impact | F5: Priority | G5: Status | H5: Owner | I5: Acceptance / Test Scenario
A6: LR-001 | B6: Rider activation | C6: When a rider is activated for a shift | D6: System blocks activation if visa/license/contract status is invalid | E6: All | F6: Critical | G6: Not Started | I6: Test rider with expired license must remain blocked
A7: LR-002 | B7: Vehicle activation | C7: When a vehicle is assigned or used | D7: System blocks use if registration/insurance/inspection is invalid | E7: All | F7: Critical | G7: Not Started | I7: Expired insurance should stop assignment
A8: LR-003 | B8: Vehicle source type | C8: When a vehicle record is created | D8: Every vehicle must have vehicle_source_type populated | E8: All | F8: Critical | G8: Not Started | I8: No vehicle can be saved without source type
A9: LR-004 | B9: Owned vehicle costing | C9: During monthly costing run | D9: Owned vehicles use depreciation + maintenance + compliance costs | E9: Owned Only | F9: High | G9: Not Started | I9: Book value and monthly cost should update
A10: LR-005 | B10: Rented vehicle costing | C10: During monthly costing run | D10: Rented vehicles use rental expense + uncovered repair + compliance costs | E10: Rented Only | F10: High | G10: Not Started | I10: Rental payable should link to vehicle
A11: LR-006 | B11: Rider-owned vehicle costing | C11: During monthly costing run | D11: Rider-owned vehicles use allowance/subsidy/support costs only | E11: Rider-Owned Only | F11: High | G11: Not Started | I11: No company asset cost should be posted
A12: LR-007 | B12: Maintenance routing | C12: When maintenance event is logged | D12: Responsible party auto-routes based on source type and contract terms | E12: All (varies by source type) | F12: Critical | G12: Not Started | I12: Supplier / company / rider routing should differ
A13: LR-008 | B13: Assignment history | C13: When rider/vehicle pairing changes | D13: System must create assignment start/end history record | E13: All | F13: Critical | G13: Not Started | I13: Previous assignment must close before new one opens
A14: LR-009 | B14: Payroll allowance/deduction | C14: When payroll is generated | D14: Vehicle-related earnings or deductions depend on source type | E14: All (varies by source type) | F14: Critical | G14: Not Started | I14: Own-bike allowance and company-bike deduction must not both apply
A15: LR-010 | B15: Breakdown replacement | C15: When a vehicle becomes unavailable mid-shift | D15: Replacement workflow differs by source type and policy | E15: All (varies by source type) | F15: High | G15: Not Started | I15: Rider-owned case may not auto-assign company backup
A16: LR-011 | B16: Order integrity | C16: When orders are imported | D16: Imported orders must map to rider, aggregator and source batch with exception handling | E16: All | F16: Critical | G16: Not Started | I16: Unmapped orders should enter exception queue
A17: LR-012 | B17: Billing reconciliation | C17: Before invoice is issued | D17: Invoice totals must tie to reconciled order and contract data | E17: All | F17: Critical | G17: Not Started | I17: Draft invoice blocked if unreconciled orders exist
... A20: LR-015 | B20: Profitability segmentation | C20: When BI/reporting refresh runs | D20: Reports must segment margin by owned, rented and rider-owned models | E20: All | F20: Critical | G20: Not Started | I20: Mixed-source report should reconcile to total margin
